{"generatedAt":"2026-07-15T20:45:37.532Z","listings":[],"requests":[{"server":"PvP","player":"Norkog","plus":[7],"stats":["str"],"category":"jewelery","text":"+7 str jewelery","seen":"2026-07-06T04:32:14.181Z","lastSeen":"2026-07-10T08:30:33.462Z","count":15},{"server":"PvE","player":"Rekles","plus":[4],"stats":["str","dex","int","wis"],"category":null,"text":"+4 enchants 5-8g each(depending on Mats): Dex:Boots/Gloves/Mask/Shoulder | Int/Wis:Helm/Neck/ Bracer | Str:Belt/Bracer/Shoulder/Legs","seen":"2026-07-06T05:36:10.144Z","lastSeen":"2026-07-08T21:34:09.719Z","count":5},{"server":"PvE","player":"Rekles","plus":[],"stats":["sta","agi","cha","mana"],"category":"ring","text":"Agi:Boots/Gloves/Belt/Cloak | Cha:Mask/Neck/Ring | Health:Chest/Ring | MR:Shoulder/Chest/Legs/Ring/Cloak | Mana:Chest | Sta: Helm/Bracer/Leg","seen":"2026-07-06T05:36:10.144Z","lastSeen":"2026-07-08T21:34:09.719Z","count":10},{"server":"PvE","player":"Bulini","plus":[7],"stats":[],"category":"jewelery","text":"Platinum Jewelery (+7/+7) have all gems.","seen":"2026-07-06T09:50:40.978Z","lastSeen":"2026-07-07T18:00:44.844Z","count":11},{"server":"PvP","player":"Orbbot","plus":[],"stats":[],"category":"gear","text":"Druid wisdom GEAR","seen":"2026-07-06T18:08:46.313Z","lastSeen":"2026-07-07T17:19:06.215Z","count":42},{"server":"PvP","player":"Vicks","plus":[4],"stats":["str","sta","agi","dex","int","wis","cha"],"category":"necklace","text":"T4 (+4) Enchants:Bracer 10g (INT/STA/WIS/STR), Necklace 5g (+4 CHA/INT/WIS), Cloak 5g (AGI), Gloves 4g (AGI/DEX), Belt 4g (AGI/STR)","seen":"2026-07-06T22:24:19.156Z","lastSeen":"2026-07-07T19:59:23.902Z","count":62},{"server":"PvE","player":"Manakea","plus":[],"stats":["str","dex"],"category":"necklace","text":"7 str dex necklace","seen":"2026-07-06T22:36:48.453Z","lastSeen":"2026-07-07T22:58:19.760Z","count":2},{"server":"PvE","player":"Rukkus","plus":[],"stats":[],"category":"jewelcraft","text":"Uncle Rukkus's FREE Jewelcrafting (300) and Disenchanting service behind West Bank! Your materials (gem, ore, astral dust), my skill! Tips are welcomed, not required!","seen":"2026-07-06T23:03:52.343Z","lastSeen":"2026-07-08T15:58:32.927Z","count":13},{"server":"PvP","player":"Herbguy","plus":[],"stats":[],"category":"ring","text":"Duneleaf/whispering sage/Ironroot PST","seen":"2026-07-07T00:58:16.320Z","lastSeen":"2026-07-08T00:51:13.286Z","count":7},{"server":"PvP","player":"Vicks","plus":[4],"stats":["str","sta","agi","dex","int","wis","cha","hp"],"category":"ring","text":"T4 (+4) Enchants: Mask 5g (CHA/DEX), Ring 10g (CHA/HP), Boots 4g (AGI/DEX), Helm 5g (INT/STA/WIS),Shoulder 8g (DEX/STR), Leg 8g (STA/STR)","seen":"2026-07-07T01:12:49.726Z","lastSeen":"2026-07-07T20:01:28.906Z","count":63},{"server":"PvE","player":"Brio","plus":[5],"stats":["str","dex"],"category":"ring","text":"Gold Earrings +5/+5 stat 60s each or 2 for 1G if I have gems Let me know what you are after and I will check. (no Gems for STR/DEX sorry)","seen":"2026-07-07T02:41:08.407Z","lastSeen":"2026-07-10T03:35:22.718Z","count":7},{"server":"PvP","player":"Fullmetall","plus":[],"stats":[],"category":"ring","text":"Duneleaf/Stranglevine/ Whispering Sage PST","seen":"2026-07-07T02:57:50.018Z","lastSeen":"2026-07-08T00:19:22.532Z","count":9},{"server":"PvP","player":"Vicks","plus":[4],"stats":["str","sta","agi","dex","int","wis","cha","hp"],"category":"ring","text":"T4 (+4) Enchants: Mask 5g (CHA/DEX), Ring 10g (CHA/HP), Boots 4g (AGI/DEX), Helm 5¢ (INT/STA/WIS),Shoulder 8g (DEX/STR), Leg 8g (STA/STR)","seen":"2026-07-07T16:58:00.898Z","lastSeen":"2026-07-07T16:58:00.898Z","count":1},{"server":"PvE","player":"Thraso","plus":[4],"stats":["cha"],"category":null,"text":"CHA +4 ENCHANT PLZ","seen":"2026-07-07T16:58:00.898Z","lastSeen":"2026-07-07T16:58:18.154Z","count":2},{"server":"PvP","player":"Vicks","plus":[4],"stats":["str","sta","agi","dex","int","wis","cha","hp"],"category":"ring","text":"T4 (+4) Enchants: Mask 5g (CHA/DEX), Ring 10g (CHA/HP), Boots 4g (AGI/DEX), Helm 5¢ (INT/STA/WIS),Shoulder 8g (DEX/STR), Leg 8¢ (STA/STR)","seen":"2026-07-07T16:58:18.154Z","lastSeen":"2026-07-07T16:58:18.154Z","count":1},{"server":"PvP","player":"Vicks","plus":[4],"stats":["str","sta","agi","dex","int","wis","cha","hp"],"category":"ring","text":"T4 (+4) Enchants: Mask 5g (CHA/DEX), Ring 10g (CHA/HP), Boots 4g (AGI/DEX), Helm 5g (INT/STA/WIS),Shoulder 8g (DEX/STR), Leg 8¢ (STA/STR)","seen":"2026-07-07T17:00:23.140Z","lastSeen":"2026-07-07T19:59:23.902Z","count":3},{"server":"PvE","player":"Adzuki","plus":[],"stats":["agi","dex"],"category":null,"text":"SK belt with DEX/AGI. 35s or less.","seen":"2026-07-07T17:04:33.198Z","lastSeen":"2026-07-07T17:04:33.198Z","count":1},{"server":"PvP","player":"Krthnk","plus":[],"stats":[],"category":"weapon","text":"low level monk H2H weapons.","seen":"2026-07-07T17:06:38.036Z","lastSeen":"2026-07-07T17:19:06.215Z","count":7},{"server":"PvE","player":"Wulfrack","plus":[],"stats":[],"category":"gear","text":"Ranger high end/Bis gear","seen":"2026-07-07T17:23:16.132Z","lastSeen":"2026-07-07T17:23:16.132Z","count":1},{"server":"PvE","player":"Pintsized","plus":[],"stats":[],"category":"weapon","text":"low level ih slashing weapon cheap","seen":"2026-07-07T17:23:16.132Z","lastSeen":"2026-07-07T17:23:16.132Z","count":1},{"server":"PvE","player":"Lungold","plus":[],"stats":["dex","int"],"category":null,"text":"any int or dex Wiz masks for sale or trade?","seen":"2026-07-07T17:33:40.490Z","lastSeen":"2026-07-07T17:33:40.490Z","count":1},{"server":"PvP","player":"Vicks","plus":[4],"stats":["str","sta","agi","dex","int","cha","hp"],"category":"ring","text":"T4 (+4) Enchants: Mask 5g (CHA/DEX), Ring 10g (CHA/HP), Boots 4g (AGI/DEX), Helm 5g (INT/STA/W/IS),Shoulder 8g (DEX/STR), Leg 8g (STA/STR)","seen":"2026-07-07T18:09:04.309Z","lastSeen":"2026-07-07T19:53:08.881Z","count":4},{"server":"PvE","player":"Quebec","plus":[],"stats":[],"category":"armor","text":"** Corrupted leather armor","seen":"2026-07-07T18:09:04.309Z","lastSeen":"2026-07-07T18:11:09.325Z","count":2},{"server":"PvP","player":"Idyll","plus":[],"stats":["wis"],"category":null,"text":"SHM Wis Helm/Hands/Waist/","seen":"2026-07-07T18:17:23.501Z","lastSeen":"2026-07-07T18:27:46.524Z","count":6},{"server":"PvE","player":"Weatherwax","plus":[],"stats":[],"category":"gear","text":"Looking for some okayish starter gear for my chanter. I have a 1g budget. Any kind souls willing to help?","seen":"2026-07-07T18:17:23.501Z","lastSeen":"2026-07-07T18:17:23.501Z","count":1},{"server":"PvE","player":"Krutch","plus":[],"stats":[],"category":"weapon","text":"Crafting Steel Weapons psT","seen":"2026-07-07T18:17:23.501Z","lastSeen":"2026-07-07T23:15:26.148Z","count":9},{"server":"PvP","player":"Orbbot","plus":[],"stats":["wis"],"category":null,"text":"DRUID WIS back waist","seen":"2026-07-07T18:19:28.021Z","lastSeen":"2026-07-07T18:29:51.123Z","count":6},{"server":"PvP","player":"Idyll","plus":[],"stats":[],"category":"jewelcraft","text":"LF Jewelcrafter to make some 7/7 sets","seen":"2026-07-07T18:29:51.123Z","lastSeen":"2026-07-07T18:42:20.876Z","count":7},{"server":"PvP","player":"Laexi","plus":[],"stats":["agi","dex","int"],"category":"ring","text":"int/stam and agi/dex rings and earings. paying well","seen":"2026-07-07T18:44:25.797Z","lastSeen":"2026-07-07T18:44:25.797Z","count":1},{"server":"PvE","player":"Enchantresse","plus":[],"stats":["int","cha"],"category":"gear","text":"inexpensive int/cha gear for enc","seen":"2026-07-07T18:44:25.797Z","lastSeen":"2026-07-07T18:44:25.797Z","count":1},{"server":"PvP","player":"Muddy","plus":[],"stats":["str","dex"],"category":"gear","text":"str/dex archer gear pst","seen":"2026-07-07T18:46:30.803Z","lastSeen":"2026-07-07T22:24:02.975Z","count":14},{"server":"PvE","player":"Krutch","plus":[],"stats":[],"category":"weapon","text":"Steel Weapons PST","seen":"2026-07-07T19:03:09.532Z","lastSeen":"2026-07-07T19:21:53.665Z","count":8},{"server":"PvE","player":"Cuttya","plus":[],"stats":["str","dex"],"category":"jewelery","text":"7/7 STR/Dex Jewelery. Also high end daggers!","seen":"2026-07-07T19:03:09.532Z","lastSeen":"2026-07-07T19:21:53.665Z","count":11},{"server":"PvE","player":"Intent","plus":[],"stats":[],"category":"gear","text":"Fighter gear, pst with price and item","seen":"2026-07-07T19:11:28.674Z","lastSeen":"2026-07-07T19:19:48.762Z","count":2},{"server":"PvE","player":"Enchantresse","plus":[],"stats":["int","cha"],"category":"gear","text":"Inexpensive int/cha gear for enchanter :)","seen":"2026-07-07T19:21:53.665Z","lastSeen":"2026-07-07T19:59:23.902Z","count":6},{"server":"PvE","player":"Aequitasium","plus":[],"stats":[],"category":"gear","text":"inexpensive druid gear. have about 60s to spend. pst :)","seen":"2026-07-07T19:26:03.489Z","lastSeen":"2026-07-07T19:28:08.502Z","count":2},{"server":"PvE","player":"Cuttya","plus":[],"stats":[],"category":"gear","text":"LF rogue gear! gloves/chest/helm/face PST","seen":"2026-07-07T19:28:08.502Z","lastSeen":"2026-07-07T19:57:18.921Z","count":12},{"server":"PvP","player":"Vicks","plus":[4],"stats":["str","sta","agi","dex","int","cha","hp"],"category":"ring","text":"W 1S 14 (+4) Enchants: Mask 5g (CHA/DEX), Ring 10g (CHA/HP), Boots 4g (AGI/DEX), Helm 5g (INT/STA/W/IS),Shoulder 8g (DEX/STR), Leg 8g (STA/STR)","seen":"2026-07-07T19:34:23.715Z","lastSeen":"2026-07-07T19:34:23.715Z","count":1},{"server":"PvE","player":"Quebec","plus":[],"stats":[],"category":"armor","text":"anyone have corrupted leather armor pieces I can buy?","seen":"2026-07-07T19:42:43.851Z","lastSeen":"2026-07-07T19:42:43.851Z","count":1},{"server":"PvP","player":"Slowking","plus":[],"stats":["sta","wis"],"category":"gear","text":"WIS/STA Gear","seen":"2026-07-07T20:09:47.951Z","lastSeen":"2026-07-07T20:13:57.315Z","count":3},{"server":"PvE","player":"Quebec","plus":[],"stats":[],"category":"armor","text":"corrupted leather armor","seen":"2026-07-07T20:09:47.951Z","lastSeen":"2026-07-07T20:16:02.056Z","count":4},{"server":"PvE","player":"Caji","plus":[],"stats":["int"],"category":"ring","text":"INT ring/gloves/wrist for a lvl 36 ELE","seen":"2026-07-07T20:11:52.608Z","lastSeen":"2026-07-07T20:16:02.056Z","count":3},{"server":"PvP","player":"Vicks","plus":[4],"stats":["str","sta","agi","dex","int","wis","cha"],"category":"necklace","text":"+4 Enchants: Bracer 10g(INT/STA/WIS/STR), Necklace 5¢(CHA/INT/WIS), Cloak 5g(AGI/8 CR/CR/PR), Gloves 4g (AGI/DEX/8 CR/ER)","seen":"2026-07-07T20:16:02.056Z","lastSeen":"2026-07-07T20:18:07.091Z","count":2},{"server":"PvP","player":"Vicks","plus":[],"stats":["str","sta","agi","dex","int","wis","cha","hp"],"category":"ring","text":"Mask 5g(CHA/DEX/8 DR/PR), Ring 10g (CHA/20 HP), Boots 4g (AGI/DEX/8 CR/FR), Helm 5g (INT/STA/WIS/8 DR),Belt 4g (AGI/STR/8 ER/HR)","seen":"2026-07-07T20:16:02.056Z","lastSeen":"2026-07-08T17:30:26.369Z","count":19},{"server":"PvP","player":"Vicks","plus":[],"stats":["str","sta","dex","cha","hp","mana","resist"],"category":"ring","text":"Shoulder 8g (DEX/STR/8 any resist), Leg 8g (STA/STR/8 any resist), Chest 8g (20 HP/20 Mana/8 FR/MR), Earring 10g (CHA/20 Mana)","seen":"2026-07-07T20:16:02.056Z","lastSeen":"2026-07-08T17:35:30.279Z","count":26},{"server":"PvE","player":"Quebec","plus":[],"stats":[],"category":"armor","text":"* * corrupted leather armor","seen":"2026-07-07T20:22:16.599Z","lastSeen":"2026-07-07T20:24:21.413Z","count":2},{"server":"PvE","player":"Shandra","plus":[],"stats":[],"category":"gear","text":"W/TB Shaman Gear. Preferable Chest and offhand","seen":"2026-07-07T20:26:26.237Z","lastSeen":"2026-07-07T20:26:26.237Z","count":1},{"server":"PvP","player":"Oliva","plus":[],"stats":["int"],"category":"gear","text":"Int caster gear, lots of g to spend","seen":"2026-07-07T20:28:31.105Z","lastSeen":"2026-07-07T20:32:41.049Z","count":3},{"server":"PvE","player":"Caji","plus":[],"stats":["int"],"category":null,"text":"INT gloves/wrist","seen":"2026-07-07T20:28:31.105Z","lastSeen":"2026-07-07T20:28:31.105Z","count":1},{"server":"PvE","player":"Stableadult","plus":[5],"stats":["cha"],"category":"jewelery","text":"anyone let me know how much +5int/cha jewelery goes for?","seen":"2026-07-07T20:32:41.049Z","lastSeen":"2026-07-07T20:32:41.049Z","count":1},{"server":"PvP","player":"Vicks","plus":[4],"stats":["str","sta","agi","dex","int","wis","cha"],"category":"necklace","text":"+4 Enchants: Bracer 10g(INT/STA/WIS/STR), Necklace 5g(CHA/INT/WIS), Cloak 5g(AGI/8 CR/CR/MR/PR), Gloves 4g (AGI/DEX/8 CR/ER)","seen":"2026-07-07T20:34:45.830Z","lastSeen":"2026-07-08T16:24:03.925Z","count":8},{"server":"PvE","player":"Lilwulf","plus":[],"stats":["wis","cha"],"category":"ring","text":"7/7 Wis+Cha Earrings","seen":"2026-07-07T20:36:51.060Z","lastSeen":"2026-07-07T22:04:46.714Z","count":2},{"server":"PvE","player":"Caji","plus":[],"stats":["int"],"category":"weapon","text":"INT 1 handed weapon, gloves, bracers!","seen":"2026-07-07T20:51:53.941Z","lastSeen":"2026-07-07T20:51:53.941Z","count":1},{"server":"PvP","player":"Stabbyripstab","plus":[],"stats":[],"category":"ring","text":"100% payment for all materials is due prior to ordering and is non- refundable once materials havebeen purchased or custom ordered by G&amp;C Representative.","seen":"2026-07-07T21:02:32.595Z","lastSeen":"2026-07-07T21:08:58.411Z","count":4},{"server":"PvE","player":"Enchantresse","plus":[],"stats":["int","cha"],"category":"gear","text":"int/cha gear for enchanter","seen":"2026-07-07T21:11:07.116Z","lastSeen":"2026-07-07T21:11:07.116Z","count":1},{"server":"PvE","player":"Grimfang","plus":[],"stats":["wis"],"category":"jewelry","text":"wis/cleric jewelry pst","seen":"2026-07-07T21:17:33.956Z","lastSeen":"2026-07-07T21:17:33.956Z","count":1},{"server":"PvP","player":"Wizronling","plus":[],"stats":["haste"],"category":null,"text":"20% haste belt!","seen":"2026-07-07T21:21:51.064Z","lastSeen":"2026-07-07T21:28:16.989Z","count":7},{"server":"PvP","player":"Idyll","plus":[],"stats":[],"category":"shield","text":"Wisd Helmet, Shield, 1h, hand, waist","seen":"2026-07-07T21:23:59.923Z","lastSeen":"2026-07-07T21:28:16.989Z","count":2},{"server":"PvP","player":"Idyll","plus":[],"stats":[],"category":"shield","text":"Wisd Helmet, Shield, th, hand, waist","seen":"2026-07-07T21:26:08.652Z","lastSeen":"2026-07-07T21:26:08.652Z","count":1},{"server":"PvE","player":"Rukkus","plus":[],"stats":[],"category":"jewelcraft","text":"Uncle Rukkus's FREE Jewelcrafting (300) and Disenchanting service behind West Bank! Your materials (gem, ore, astral dust), my skill! Tips are welcomed, no required!","seen":"2026-07-07T21:34:44.484Z","lastSeen":"2026-07-08T23:39:22.708Z","count":8},{"server":"PvE","player":"Mukkuk","plus":[],"stats":["int"],"category":null,"text":"Wiz INT bracers/belt/pants/pri/sec in the 5g price range","seen":"2026-07-07T21:36:53.040Z","lastSeen":"2026-07-07T21:36:53.040Z","count":1},{"server":"PvP","player":"Earsnot","plus":[2],"stats":["wis"],"category":"ring","text":"Anyone selling +2 or better WIS items for like 50s a piece or less? Looking for ears, rings, gloves, belt, wrists -P","seen":"2026-07-07T21:39:01.681Z","lastSeen":"2026-07-07T21:39:01.681Z","count":1},{"server":"PvE","player":"Exit","plus":[],"stats":["str","sta"],"category":"ring","text":"STR/STA earings PST","seen":"2026-07-07T21:39:01.681Z","lastSeen":"2026-07-07T21:41:09.611Z","count":2},{"server":"PvE","player":"Supermiguel","plus":[],"stats":[],"category":"weapon","text":"steel weapon","seen":"2026-07-07T21:39:01.681Z","lastSeen":"2026-07-07T21:41:09.611Z","count":2},{"server":"PvP","player":"Spor","plus":[],"stats":["wis"],"category":null,"text":"higher end shaman wis bracers","seen":"2026-07-07T21:43:18.407Z","lastSeen":"2026-07-07T21:45:27.195Z","count":2},{"server":"PvP","player":"Wickedwolf","plus":[],"stats":["dex","cha"],"category":"jewelry","text":"dex/cha jewelry.","seen":"2026-07-07T21:58:21.060Z","lastSeen":"2026-07-07T22:17:37.216Z","count":10},{"server":"PvE","player":"Ahlucard","plus":[],"stats":["str","dex"],"category":"jewelery","text":"Str/Dex Jewelery","seen":"2026-07-07T21:58:21.060Z","lastSeen":"2026-07-07T21:58:21.060Z","count":1},{"server":"PvE","player":"Goeji","plus":[],"stats":[],"category":"gear","text":"lower level charisma gear for ench. need shoulders, back, gloves, waist, wrist, and head","seen":"2026-07-07T22:00:29.423Z","lastSeen":"2026-07-08T23:12:14.884Z","count":2},{"server":"PvE","player":"Ahlucard","plus":[],"stats":["str","dex"],"category":"jewelry","text":"Str/Dex Jewelry","seen":"2026-07-07T22:00:29.423Z","lastSeen":"2026-07-07T22:00:29.423Z","count":1},{"server":"PvP","player":"Bevins","plus":[],"stats":["int","mana"],"category":"gear","text":"+int/mana Ele gear","seen":"2026-07-07T22:15:28.711Z","lastSeen":"2026-07-07T22:24:02.975Z","count":5},{"server":"PvE","player":"Goron","plus":[],"stats":[],"category":"jewelry","text":"platinum jewelry pst","seen":"2026-07-07T22:15:28.711Z","lastSeen":"2026-07-07T22:15:28.711Z","count":1},{"server":"PvE","player":"Vegtastik","plus":[],"stats":[],"category":"armor","text":"armor enchants","seen":"2026-07-07T22:17:37.216Z","lastSeen":"2026-07-08T00:34:15.397Z","count":5},{"server":"PvE","player":"Pippi","plus":[4],"stats":["sta"],"category":null,"text":"+4 sta legs enchant pst","seen":"2026-07-07T22:30:27.820Z","lastSeen":"2026-07-08T21:48:46.197Z","count":3},{"server":"PvE","player":"Supermiguel","plus":[],"stats":["str"],"category":"gear","text":"plate gear with +STR cheap :) tank/ftr here","seen":"2026-07-07T22:32:36.162Z","lastSeen":"2026-07-07T22:32:36.162Z","count":1},{"server":"PvP","player":"Vicks","plus":[4],"stats":["str","sta","agi","dex","int","wis","cha"],"category":"necklace","text":"+4 Enchants: Bracer 10g(INT/STA/WIS/STR), Necklace 5¢(CHA/INT/WIS), Cloak 5g(AGI/8 CR/CR/MR/PR), Gloves 4g (AGI/DEX/8 CR/ER)","seen":"2026-07-07T22:43:18.561Z","lastSeen":"2026-07-08T17:30:26.369Z","count":7},{"server":"PvE","player":"Zhang","plus":[],"stats":[],"category":"armor","text":"Full set of Enchanted Armor (Head , Legs , Chest) Cloth, Rawhide, Copper (Chain or Plate) 1.2g","seen":"2026-07-07T22:45:27.162Z","lastSeen":"2026-07-07T22:45:27.162Z","count":1},{"server":"PvE","player":"Keeds","plus":[],"stats":[],"category":"gear","text":"monk gear that isn't too expensive i'm level 10 and poor","seen":"2026-07-07T22:47:35.830Z","lastSeen":"2026-07-07T22:47:35.830Z","count":1},{"server":"PvP","player":"Vicks","plus":[],"stats":["str","sta","agi","dex","int","wis","cha","hp"],"category":"ring","text":"Mask 5g(CHA/DEX/8 DR/PR), Ring 10g (CHA/20 HP), Boots 4g (AGI/DEX/8 CR/ER), Helm 5g (INT/STA/WIS/8 DR),Belt 4g (AGI/STR/8 ER/HR)","seen":"2026-07-07T22:51:53.367Z","lastSeen":"2026-07-07T22:51:53.367Z","count":1},{"server":"PvP","player":"Bevins","plus":[],"stats":["sta","hp"],"category":"ring","text":"low level +sta/+hp earrings,neck,rings","seen":"2026-07-07T22:56:11.452Z","lastSeen":"2026-07-07T22:58:19.760Z","count":2},{"server":"PvE","player":"Xanza","plus":[],"stats":["int"],"category":null,"text":"int wrists/legs","seen":"2026-07-07T22:58:19.760Z","lastSeen":"2026-07-07T23:02:36.622Z","count":3},{"server":"PvP","player":"Idyll","plus":[],"stats":[],"category":"gear","text":"Anyone got shaman gear they want to sell?","seen":"2026-07-07T23:09:01.487Z","lastSeen":"2026-07-07T23:17:34.832Z","count":5},{"server":"PvP","player":"Idyll","plus":[],"stats":[],"category":"jewelery","text":"Crafted 7/7 Jewelery Set","seen":"2026-07-07T23:17:34.832Z","lastSeen":"2026-07-07T23:23:59.458Z","count":4},{"server":"PvE","player":"Force","plus":[],"stats":["dmg","regen"],"category":"shield","text":"tipping for dmg shield/regen 36+ pref","seen":"2026-07-07T23:21:51.319Z","lastSeen":"2026-07-07T23:21:51.319Z","count":1},{"server":"PvE","player":"Limestone","plus":[],"stats":["wis","mana"],"category":null,"text":"wis/mana gloves and/or cloak, under 1.5g PST","seen":"2026-07-07T23:21:51.319Z","lastSeen":"2026-07-07T23:21:51.319Z","count":1},{"server":"PvE","player":"Enchantresse","plus":[],"stats":["int","cha"],"category":"gear","text":"Low-Mid tier int/cha gear for Enc","seen":"2026-07-07T23:21:51.319Z","lastSeen":"2026-07-07T23:23:59.458Z","count":2},{"server":"PvE","player":"Force","plus":[],"stats":["wis"],"category":"gear","text":"low end wis gear","seen":"2026-07-07T23:26:08.013Z","lastSeen":"2026-07-07T23:26:08.013Z","count":1},{"server":"PvP","player":"Zangief","plus":[],"stats":[],"category":"gear","text":"higher end spellblade gear/weps pst","seen":"2026-07-07T23:30:23.995Z","lastSeen":"2026-07-07T23:39:00.440Z","count":6},{"server":"PvE","player":"Force","plus":[],"stats":["wis"],"category":"gear","text":"low end wis gear for dru","seen":"2026-07-07T23:58:07.597Z","lastSeen":"2026-07-07T23:58:07.597Z","count":1},{"server":"PvE","player":"Essynne","plus":[],"stats":["int"],"category":"gear","text":"wizard INT gear for face slot PST","seen":"2026-07-08T00:04:32.766Z","lastSeen":"2026-07-08T00:06:39.022Z","count":2},{"server":"PvP","player":"Fullmetall","plus":[],"stats":[],"category":"ring","text":"TB Duneleaf/Stranglevine/ Whispering Sage PST","seen":"2026-07-08T00:10:52.878Z","lastSeen":"2026-07-08T00:10:52.878Z","count":1},{"server":"PvE","player":"Slaygi","plus":[],"stats":[],"category":"ring","text":"starter rogue wrists, rings","seen":"2026-07-08T00:10:52.878Z","lastSeen":"2026-07-08T00:12:59.398Z","count":2},{"server":"PvP","player":"Fullmetall","plus":[],"stats":[],"category":"ring","text":"/TB Duneleaf/Stranglevine/ Whispering Sage PST","seen":"2026-07-08T00:15:07.424Z","lastSeen":"2026-07-08T00:15:07.424Z","count":1},{"server":"PvE","player":"Supermiguel","plus":[],"stats":["str","dex"],"category":"gear","text":"+STR +DEX gear","seen":"2026-07-08T00:19:22.532Z","lastSeen":"2026-07-08T00:19:22.532Z","count":1},{"server":"PvP","player":"Bandages","plus":[],"stats":["int"],"category":"gear","text":"+int gear","seen":"2026-07-08T00:21:30.259Z","lastSeen":"2026-07-08T00:38:29.849Z","count":9},{"server":"PvE","player":"Darkmoon","plus":[],"stats":[],"category":"armor","text":"Seeking blacksmith for horse armor","seen":"2026-07-08T00:21:30.259Z","lastSeen":"2026-07-08T00:23:37.906Z","count":2},{"server":"PvP","player":"Bandages","plus":[],"stats":["int"],"category":"gear","text":"+ int gear","seen":"2026-07-08T00:27:52.779Z","lastSeen":"2026-07-08T00:40:37.279Z","count":7},{"server":"PvE","player":"Sekcey","plus":[],"stats":["wis"],"category":null,"text":"druid wis bracer pst","seen":"2026-07-08T00:32:08.225Z","lastSeen":"2026-07-08T00:36:22.674Z","count":2},{"server":"PvP","player":"Bandages","plus":[],"stats":["str"],"category":"gear","text":"+str gear","seen":"2026-07-08T00:34:15.397Z","lastSeen":"2026-07-08T00:42:44.466Z","count":5},{"server":"PvP","player":"Bandages","plus":[],"stats":["int"],"category":null,"text":"+int*","seen":"2026-07-08T00:34:15.397Z","lastSeen":"2026-07-08T00:44:51.405Z","count":6},{"server":"PvE","player":"Enchantresse","plus":[],"stats":["int","cha"],"category":"gear","text":"Int/cha gear for an enc","seen":"2026-07-08T00:36:22.674Z","lastSeen":"2026-07-08T00:36:22.674Z","count":1},{"server":"PvP","player":"Norkog","plus":[7],"stats":[],"category":"jewelery","text":"+7 jewelery pst","seen":"2026-07-08T14:34:50.633Z","lastSeen":"2026-07-10T04:12:51.911Z","count":39},{"server":"PvE","player":"Meek","plus":[],"stats":["int"],"category":"gear","text":"int caster (necro) gear - waist, wrist, and back","seen":"2026-07-08T14:34:50.633Z","lastSeen":"2026-07-09T11:48:11.430Z","count":5},{"server":"PvE","player":"Stakilm","plus":[],"stats":["int"],"category":"gear","text":"Low level int \"elementalist\" gear, I'm not rich","seen":"2026-07-08T14:45:21.606Z","lastSeen":"2026-07-08T14:45:21.606Z","count":1},{"server":"PvE","player":"Stakilm","plus":[],"stats":["int"],"category":"gear","text":"Low level int \"elementalist” gear, I'm not rich","seen":"2026-07-08T14:47:28.103Z","lastSeen":"2026-07-08T14:47:28.103Z","count":1},{"server":"PvE","player":"Goron","plus":[],"stats":["str","dex"],"category":"jewelry","text":"full set of platinum 7/7 str/dex jewelry 32g pst","seen":"2026-07-08T14:47:28.103Z","lastSeen":"2026-07-08T14:47:28.103Z","count":1},{"server":"PvE","player":"Bulini","plus":[7],"stats":[],"category":"jewelry","text":"Platinum Jewelry (+7/+7) have all gems.","seen":"2026-07-08T14:49:33.296Z","lastSeen":"2026-07-09T14:40:21.862Z","count":9},{"server":"PvP","player":"Boisterous","plus":[7],"stats":["cha"],"category":"ring","text":"+7/7 CHA rings","seen":"2026-07-08T15:19:38.972Z","lastSeen":"2026-07-08T15:36:47.302Z","count":9},{"server":"PvP","player":"Nolletta","plus":[],"stats":["int","cha"],"category":"gear","text":"W/TB Cha/Int Gear Bracers, shoulders, back PST stats/price","seen":"2026-07-08T15:41:06.946Z","lastSeen":"2026-07-08T15:56:25.390Z","count":6},{"server":"PvP","player":"Nolletta","plus":[],"stats":["int","cha"],"category":"gear","text":"Cha/Int Gear Bracers, shoulders, back PST stats/price","seen":"2026-07-08T15:43:16.680Z","lastSeen":"2026-07-08T15:49:44.481Z","count":2},{"server":"PvP","player":"Noletta","plus":[],"stats":["int","cha"],"category":"gear","text":"W 1B Cha/Int Gear Bracers, shoulders, back PS1 stats/price","seen":"2026-07-08T15:45:27.318Z","lastSeen":"2026-07-08T15:56:25.390Z","count":2},{"server":"PvE","player":"Timothee","plus":[],"stats":[],"category":"ring","text":"1 plat cats eye earring, 2 cats eye plat Ring pst","seen":"2026-07-08T15:56:25.390Z","lastSeen":"2026-07-08T15:56:25.390Z","count":1},{"server":"PvP","player":"Nolletta","plus":[],"stats":["int","cha"],"category":"gear","text":"TB Cha/Int Gear Bracers, shoulders, back PST stats/price","seen":"2026-07-08T15:58:32.927Z","lastSeen":"2026-07-08T15:58:32.927Z","count":1},{"server":"PvE","player":"Enchantresse","plus":[5],"stats":["int","cha"],"category":"jewelry","text":"full set of +5 int/cha jewelry","seen":"2026-07-08T16:21:53.706Z","lastSeen":"2026-07-08T16:50:16.223Z","count":4},{"server":"PvP","player":"Reaperz","plus":[],"stats":[],"category":"jewellery","text":"LF Jeweller to make 7/7 jewellery have mats","seen":"2026-07-08T16:26:11.662Z","lastSeen":"2026-07-08T17:28:20.818Z","count":30},{"server":"PvE","player":"Vanilly","plus":[],"stats":["heal"],"category":"weapon","text":"nice druid weapon to sit on my lap while i heal","seen":"2026-07-08T16:32:52.522Z","lastSeen":"2026-07-08T16:39:29.499Z","count":4},{"server":"PvE","player":"Intent","plus":[],"stats":[],"category":"ring","text":"Fighter BP, Belt, Rings PST","seen":"2026-07-08T16:54:26.764Z","lastSeen":"2026-07-08T16:56:32.178Z","count":2},{"server":"PvE","player":"Gerbanzo","plus":[],"stats":["int"],"category":null,"text":"cheap NEC INT: Face, Belt, Gloves. I have 1.5g to spend and would love all slots filled.","seen":"2026-07-08T17:11:14.708Z","lastSeen":"2026-07-08T17:13:20.055Z","count":2},{"server":"PvE","player":"Montecore","plus":[],"stats":[],"category":"gear","text":"Looking for Shaman gear Face/Cloak/Boots/Belt","seen":"2026-07-08T17:11:14.708Z","lastSeen":"2026-07-08T17:13:20.055Z","count":2},{"server":"PvE","player":"Fubs","plus":[],"stats":[],"category":"ring","text":"Stirring Stick/Savage Club","seen":"2026-07-08T17:15:25.617Z","lastSeen":"2026-07-08T17:30:26.369Z","count":3},{"server":"PvE","player":"Gundula","plus":[],"stats":[],"category":"ring","text":"anyone offering chest / legs / weapon / shield enchants?","seen":"2026-07-08T17:15:25.617Z","lastSeen":"2026-07-08T17:17:50.972Z","count":2},{"server":"PvE","player":"Elcid","plus":[],"stats":["dex"],"category":null,"text":"Greater Charisma and Dex Helm enchant","seen":"2026-07-08T17:24:10.256Z","lastSeen":"2026-07-08T17:26:15.529Z","count":2},{"server":"PvE","player":"Erevaniel","plus":[],"stats":[],"category":"weapon","text":"looking for a primary weapon for bard scrounged together 55 silver LoL","seen":"2026-07-08T17:30:26.369Z","lastSeen":"2026-07-08T17:30:26.369Z","count":1},{"server":"PvP","player":"Foe","plus":[],"stats":["int"],"category":"gear","text":"Int gear","seen":"2026-07-08T17:41:45.990Z","lastSeen":"2026-07-08T17:50:06.814Z","count":5},{"server":"PvE","player":"Fubs","plus":[],"stats":[],"category":"ring","text":"Savage club/Stirring stick","seen":"2026-07-08T17:52:11.983Z","lastSeen":"2026-07-08T17:52:11.983Z","count":1},{"server":"PvE","player":"Silverleaves","plus":[],"stats":[],"category":"weapon","text":"steel weapons or anything a tiny bit better, ranger 1 handed weapon","seen":"2026-07-08T18:16:06.233Z","lastSeen":"2026-07-08T18:18:11.452Z","count":2},{"server":"PvE","player":"Meek","plus":[],"stats":["int"],"category":null,"text":"int caster (necro) back, waist, and wrist.","seen":"2026-07-08T18:37:02.097Z","lastSeen":"2026-07-08T18:47:40.636Z","count":4},{"server":"PvE","player":"Luteanddrum","plus":[],"stats":["cha"],"category":"ring","text":"CHA earrings PST","seen":"2026-07-08T18:49:46.599Z","lastSeen":"2026-07-08T19:14:13.934Z","count":4},{"server":"PvP","player":"Pickleschanter","plus":[],"stats":[],"category":"gear","text":"anyone have some cheap ench gear for sale?","seen":"2026-07-08T19:00:23.527Z","lastSeen":"2026-07-08T19:00:23.527Z","count":1},{"server":"PvP","player":"Vicks","plus":[4],"stats":["str","sta","agi","dex","int","wis","cha"],"category":"necklace","text":"+4 Enchants: Bracer 20g(INT/STA/WIS/STR), Necklace 7g(CHA/INT/WIS), Cloak 7g(AGI/8 CR/CR/MR/PR), Gloves 6g (AGI/DEX/8 CR/ER)","seen":"2026-07-08T19:05:42.920Z","lastSeen":"2026-07-10T06:45:01.542Z","count":74},{"server":"PvP","player":"Vicks","plus":[],"stats":["str","sta","agi","dex","int","wis","cha","hp"],"category":"ring","text":"Mask 7g(CHA/DEX/8 DR/PR), Ring 20g (CHA/20 HP), Boots 6g (AGI/DEX/8 CR/FR), Helm 7g (INT/STA/WIS/8 DR),Belt 6g (AGI/STR/8 ER/HR)","seen":"2026-07-08T19:05:42.920Z","lastSeen":"2026-07-10T06:45:01.542Z","count":87},{"server":"PvP","player":"Vicks","plus":[],"stats":["str","sta","dex","cha","hp","mana","resist"],"category":"ring","text":"Shoulder 14g (DEX/STR/8 any resist), Leg 14g (STA/STR/8 any resist), Chest 14g (20 HP/20 Mana/8 FR/MR), Earring 20g (CHA/20 Mana)","seen":"2026-07-08T19:05:42.920Z","lastSeen":"2026-07-08T19:07:48.520Z","count":2},{"server":"PvP","player":"Vicks","plus":[],"stats":["str","sta","agi","dex","int","wis","cha","hp"],"category":"ring","text":"Mask /7g(CHA/DEX/8 DR/PR), Ring 20g (CHA/2U HP), Boots 6g (AGI/DEX/8 CR/FR), Helm 7g (INT/STA/WIS/8 DR),Belt 6g (AGI/STR/8 ER/HR)","seen":"2026-07-08T19:07:48.520Z","lastSeen":"2026-07-08T19:07:48.520Z","count":1},{"server":"PvE","player":"Ruinruned","plus":[],"stats":[],"category":"ring","text":"low end sapphire ring and earing","seen":"2026-07-08T19:07:48.520Z","lastSeen":"2026-07-08T19:20:29.354Z","count":3},{"server":"PvP","player":"Gnomerica","plus":[],"stats":["str","sta"],"category":"jewelry","text":"on 7/7 jewelry approx? (specifically amber str/sta)","seen":"2026-07-08T19:10:03.516Z","lastSeen":"2026-07-08T19:14:13.934Z","count":3},{"server":"PvP","player":"Vicks","plus":[],"stats":["str","sta","dex","resist"],"category":null,"text":"Shoulder 14g (DEX/STR/8 any resist), Leg 14g (STA/STR/8 any resist)","seen":"2026-07-08T19:18:24.035Z","lastSeen":"2026-07-10T06:47:14.807Z","count":107},{"server":"PvP","player":"Idyll","plus":[],"stats":[],"category":"weapon","text":"Strong 2h Weapon 29+ PST","seen":"2026-07-08T19:22:34.456Z","lastSeen":"2026-07-08T19:22:34.456Z","count":1},{"server":"PvE","player":"Snadgang","plus":[3],"stats":[],"category":"jewelry","text":"/Interested in purchasing +3 Hematite Jewelry!","seen":"2026-07-08T19:30:55.694Z","lastSeen":"2026-07-08T19:30:55.694Z","count":1},{"server":"PvE","player":"Snadgang","plus":[3],"stats":["dex","int"],"category":"jewelry","text":"Int/Dex Jewelry +3/3","seen":"2026-07-08T19:33:01.116Z","lastSeen":"2026-07-08T19:33:01.116Z","count":1},{"server":"PvP","player":"Idyll","plus":[],"stats":[],"category":"gear","text":"SK Gear Imk what you have!","seen":"2026-07-08T19:39:17.043Z","lastSeen":"2026-07-08T19:41:22.347Z","count":2},{"server":"PvP","player":"Krit","plus":[],"stats":["str","dex"],"category":null,"text":"Chainmail piece for rogue str and dex","seen":"2026-07-08T19:39:17.043Z","lastSeen":"2026-07-08T19:41:22.347Z","count":2},{"server":"PvE","player":"Snadgang","plus":[3],"stats":["dex","int"],"category":"jewelry","text":"Int/Dex jewelry +3","seen":"2026-07-08T19:39:17.043Z","lastSeen":"2026-07-08T19:41:22.347Z","count":2},{"server":"PvP","player":"Vicks","plus":[4],"stats":["agi","dex","int","wis","cha"],"category":"necklace","text":"W 1S +4 Enchants: Bracer ZUgUN1/S1A/ W1S/S TR), Necklace 7g(CHA/INT/WIS), Cloak 7g(AGI/8 CR/CR/MR/PR), Gloves 6g (AGI/DEX/8 CR/ER)","seen":"2026-07-08T19:43:27.639Z","lastSeen":"2026-07-08T19:43:27.639Z","count":1},{"server":"PvE","player":"Keeds","plus":[7],"stats":[],"category":"jewelry","text":"+7agi+7dex jewelry","seen":"2026-07-08T19:43:27.639Z","lastSeen":"2026-07-08T19:43:27.639Z","count":1},{"server":"PvE","player":"Onlynukes","plus":[],"stats":[],"category":"weapon","text":"Anyone on can make steel weapons?","seen":"2026-07-08T19:43:27.639Z","lastSeen":"2026-07-08T19:45:33.666Z","count":2},{"server":"PvE","player":"Snadgang","plus":[2],"stats":["dex","int"],"category":"jewelry","text":"Int/Dex jewelry ether +2/2~3/3~4/4","seen":"2026-07-08T19:49:44.338Z","lastSeen":"2026-07-08T19:49:44.338Z","count":1},{"server":"PvP","player":"Mafzil","plus":[4],"stats":["cha"],"category":"ring","text":"+4 cha enchant for earings!","seen":"2026-07-08T20:00:11.794Z","lastSeen":"2026-07-08T20:10:38.987Z","count":6},{"server":"PvE","player":"Zar","plus":[],"stats":["cha"],"category":null,"text":"+cha to mask enchant","seen":"2026-07-08T20:29:28.107Z","lastSeen":"2026-07-08T20:39:54.309Z","count":2},{"server":"PvP","player":"Cheez","plus":[],"stats":["str","agi","dex"],"category":"gear","text":"rouge gear str/dex/agi pst anything you got","seen":"2026-07-08T20:37:49.041Z","lastSeen":"2026-07-08T20:39:54.309Z","count":2},{"server":"PvE","player":"Mendarin","plus":[],"stats":[],"category":"gear","text":"high end ranger gear (bow/weapons/chest/bracers)","seen":"2026-07-08T20:39:54.309Z","lastSeen":"2026-07-08T20:39:54.309Z","count":1},{"server":"PvE","player":"Stakilm","plus":[3],"stats":["dex","int"],"category":"jewelry","text":"low level Elementalist armor, Int/dex jewelry +3?","seen":"2026-07-08T20:48:14.902Z","lastSeen":"2026-07-08T20:48:14.902Z","count":1},{"server":"PvE","player":"Stakilm","plus":[],"stats":["dex","int"],"category":"jewelry","text":"newbie Elementalist Armor, Jewelry int/dex :)","seen":"2026-07-08T20:52:25.371Z","lastSeen":"2026-07-08T20:52:25.371Z","count":1},{"server":"PvE","player":"Britta","plus":[],"stats":["int"],"category":null,"text":"Int Wrist - Elem","seen":"2026-07-08T20:52:25.371Z","lastSeen":"2026-07-08T20:54:30.490Z","count":2},{"server":"PvE","player":"Britta","plus":[],"stats":["int"],"category":null,"text":"Int Wrist and Face item - Elem","seen":"2026-07-08T20:54:30.490Z","lastSeen":"2026-07-08T20:54:30.490Z","count":1},{"server":"PvE","player":"Enchantresse","plus":[5],"stats":["int","cha"],"category":"jewelry","text":"+5 int/cha jewelry","seen":"2026-07-08T20:56:35.624Z","lastSeen":"2026-07-08T20:56:35.624Z","count":1},{"server":"PvE","player":"Stakilm","plus":[],"stats":["dex","int"],"category":"jewelry","text":"Newbie caster Armor & jewelry, int+stam/dex","seen":"2026-07-08T21:00:45.843Z","lastSeen":"2026-07-08T21:00:45.843Z","count":1},{"server":"PvE","player":"Consoom","plus":[],"stats":[],"category":"gear","text":"shaman wisdom gear, armor, wep/shield","seen":"2026-07-08T21:09:07.502Z","lastSeen":"2026-07-08T21:09:07.502Z","count":1},{"server":"PvE","player":"Brio","plus":[],"stats":["mana"],"category":null,"text":"Brilliant Crystallized Mana or Mystic Fond 1G","seen":"2026-07-08T21:17:28.482Z","lastSeen":"2026-07-08T21:17:28.482Z","count":1},{"server":"PvE","player":"Nukki","plus":[],"stats":[],"category":"ring","text":"| 2x 7str/7agi earings and 1 7str/7dex necklace","seen":"2026-07-08T21:17:28.482Z","lastSeen":"2026-07-08T22:13:49.672Z","count":3},{"server":"PvP","player":"Orgok","plus":[5],"stats":["str","sta","agi"],"category":"ring","text":"min +5 STR/AGI or STA/AGI earrings","seen":"2026-07-08T21:27:54.162Z","lastSeen":"2026-07-08T21:29:59.180Z","count":2},{"server":"PvE","player":"Artihen","plus":[],"stats":[],"category":"armor","text":"bard armor pst","seen":"2026-07-08T21:32:04.441Z","lastSeen":"2026-07-08T21:32:04.441Z","count":1},{"server":"PvE","player":"Itangast","plus":[],"stats":[],"category":"jeweler","text":"Any new Jeweler wants some Chipped gems FREE? PST","seen":"2026-07-08T21:40:25.683Z","lastSeen":"2026-07-08T21:40:25.683Z","count":1},{"server":"PvE","player":"Stakilm","plus":[],"stats":["int"],"category":"jewelry","text":"lowbie int armor/jewelry","seen":"2026-07-08T21:48:46.197Z","lastSeen":"2026-07-08T21:48:46.197Z","count":1},{"server":"PvP","player":"Teabeard","plus":[],"stats":["int","cha"],"category":"gear","text":"INT/CHA jewelery and Enchanter gear, PST","seen":"2026-07-08T22:15:54.949Z","lastSeen":"2026-07-08T22:20:06.200Z","count":3},{"server":"PvE","player":"Nukki","plus":[],"stats":[],"category":"necklace","text":"W/TB 7str/7dex necklace","seen":"2026-07-08T22:24:16.603Z","lastSeen":"2026-07-08T22:24:16.603Z","count":1},{"server":"PvE","player":"Nukki","plus":[],"stats":[],"category":"necklace","text":"7str/7dex necklace","seen":"2026-07-08T22:26:21.782Z","lastSeen":"2026-07-09T01:24:01.511Z","count":3},{"server":"PvP","player":"Teabeard","plus":[],"stats":["int","cha"],"category":"gear","text":"INT/CHA Jewelry and other Enchanter gear, PST","seen":"2026-07-08T22:36:47.770Z","lastSeen":"2026-07-08T22:40:58.012Z","count":3},{"server":"PvP","player":"Nolletta","plus":[],"stats":["int","cha"],"category":"gear","text":"W/TB Int/Cha Gear Chest, Shoulders, Bracers, Back PST stats/price","seen":"2026-07-08T22:38:52.977Z","lastSeen":"2026-07-09T01:24:01.511Z","count":2},{"server":"PvP","player":"Nolletta","plus":[],"stats":["int","cha"],"category":"gear","text":"Int/Cha Gear Chest, Shoulders, Bracers, Back PST stats/price","seen":"2026-07-08T22:40:58.012Z","lastSeen":"2026-07-09T01:48:19.457Z","count":12},{"server":"PvE","player":"Grevenilvec","plus":[],"stats":[],"category":"weapon","text":"cheap weapon for high cost","seen":"2026-07-08T22:59:44.303Z","lastSeen":"2026-07-08T23:03:54.359Z","count":3},{"server":"PvE","player":"Greymatter","plus":[],"stats":[],"category":"gear","text":"Clr gear Wrist/Waist/Shoulder/Face/Legs/Feet/Secondary","seen":"2026-07-08T23:10:09.571Z","lastSeen":"2026-07-08T23:18:31.065Z","count":3},{"server":"PvE","player":"Goeji","plus":[],"stats":["int"],"category":"gear","text":"lower level charisma and int gear for ench. need shoulders, back, gloves, waist, wrist, and head","seen":"2026-07-08T23:16:25.553Z","lastSeen":"2026-07-08T23:22:41.392Z","count":2},{"server":"PvP","player":"Ebola","plus":[],"stats":[],"category":"gear","text":"high end spb gear","seen":"2026-07-08T23:18:31.065Z","lastSeen":"2026-07-10T07:40:11.254Z","count":31},{"server":"PvE","player":"Wermm","plus":[],"stats":[],"category":"gear","text":"Tank gear","seen":"2026-07-08T23:22:41.392Z","lastSeen":"2026-07-08T23:22:41.392Z","count":1},{"server":"PvP","player":"Vicks","plus":[4],"stats":["str","sta","agi","dex","int","wis","cha"],"category":"necklace","text":"+4 Enchants: Bracer 20g(INT/STA/WIS/STR), Necklace 7¢(CHA/INT/WIS), Cloak 7g(AGI/8 CR/CR/MR/PR), Gloves 6g (AGI/DEX/8 CR/ER)","seen":"2026-07-08T23:26:51.774Z","lastSeen":"2026-07-10T04:48:13.334Z","count":3},{"server":"PvP","player":"Kingnether","plus":[],"stats":[],"category":"gear","text":"GEAR FOR SHM pst","seen":"2026-07-08T23:31:02.099Z","lastSeen":"2026-07-08T23:37:17.573Z","count":4},{"server":"PvE","player":"Wermm","plus":[],"stats":[],"category":"weapon","text":"Tank weapon","seen":"2026-07-08T23:31:02.099Z","lastSeen":"2026-07-09T23:32:29.598Z","count":2},{"server":"PvE","player":"Thraso","plus":[],"stats":["haste"],"category":null,"text":"10 % haste cloak plz","seen":"2026-07-08T23:37:17.573Z","lastSeen":"2026-07-08T23:37:17.573Z","count":1},{"server":"PvE","player":"Wulfrack","plus":[],"stats":["str"],"category":null,"text":"Str potions","seen":"2026-07-08T23:43:33.176Z","lastSeen":"2026-07-08T23:43:33.176Z","count":1},{"server":"PvE","player":"Sekcey","plus":[],"stats":["wis"],"category":null,"text":"druid wis off hand pst","seen":"2026-07-08T23:49:48.799Z","lastSeen":"2026-07-08T23:49:48.799Z","count":1},{"server":"PvP","player":"Idylll","plus":[],"stats":["str","dex"],"category":"ring","text":"anyone got 3/3 4/4 dex/str rings neck I can buy dont want to spend a lot","seen":"2026-07-09T01:17:23.749Z","lastSeen":"2026-07-09T01:24:01.511Z","count":3},{"server":"PvE","player":"Foulo","plus":[],"stats":[],"category":"jewelcraft","text":"Foulo's 7/7 jewelcrafting service you bring the gem and i craft wathever you want 1g for earing 1.5g for necklace and ring","seen":"2026-07-09T01:19:36.015Z","lastSeen":"2026-07-09T02:54:42.102Z","count":19},{"server":"PvP","player":"Idyll","plus":[],"stats":["str","dex"],"category":"ring","text":"anyone got 3/3 4/4 dex/str rings neck I can buy dont want to spend a lot","seen":"2026-07-09T01:21:49.165Z","lastSeen":"2026-07-09T01:21:49.165Z","count":1},{"server":"PvE","player":"Nukki","plus":[],"stats":[],"category":"necklace","text":"7str/7dex necklace, fire emerald","seen":"2026-07-09T01:26:10.872Z","lastSeen":"2026-07-09T01:26:10.872Z","count":1},{"server":"PvE","player":"Fizzle","plus":[],"stats":["wis"],"category":null,"text":"lowbie wis things, cleric plate","seen":"2026-07-09T01:59:22.774Z","lastSeen":"2026-07-09T01:59:22.774Z","count":1},{"server":"PvE","player":"Meek","plus":[],"stats":["int"],"category":"gear","text":"int caster gear (necro) waist, wrist, and back","seen":"2026-07-09T02:05:59.254Z","lastSeen":"2026-07-09T02:08:12.333Z","count":2},{"server":"PvE","player":"Meek","plus":[],"stats":["int"],"category":"gear","text":"int caster gear (necro) waist, wrist, and back!","seen":"2026-07-09T02:30:24.254Z","lastSeen":"2026-07-09T19:33:06.382Z","count":7},{"server":"PvP","player":"Rodnee","plus":[],"stats":[],"category":"weapon","text":"2h weapon ~8g","seen":"2026-07-09T02:39:18.870Z","lastSeen":"2026-07-09T03:19:01.900Z","count":14},{"server":"PvE","player":"Ricosuave","plus":[],"stats":["dex"],"category":null,"text":"full set 7str/dex - 32 Gold","seen":"2026-07-09T02:39:18.870Z","lastSeen":"2026-07-09T02:50:20.350Z","count":2},{"server":"PvE","player":"Harborfreight","plus":[],"stats":["str","cha"],"category":null,"text":"Greater Belt: Str, Greater Mask Cha enchants","seen":"2026-07-09T02:56:55.318Z","lastSeen":"2026-07-09T03:01:23.318Z","count":2},{"server":"PvE","player":"Xibat","plus":[],"stats":[],"category":"gear","text":"Ranger gear Face Wrists Belt Helm","seen":"2026-07-09T03:01:23.318Z","lastSeen":"2026-07-09T03:01:23.318Z","count":1},{"server":"PvP","player":"Piquant","plus":[],"stats":[],"category":"armor","text":"bronze/iron plate armor","seen":"2026-07-09T03:19:01.900Z","lastSeen":"2026-07-09T03:29:54.054Z","count":6},{"server":"PvP","player":"Saucy","plus":[],"stats":["sta","int"],"category":"gear","text":"INT/STA Gear","seen":"2026-07-09T03:21:12.566Z","lastSeen":"2026-07-09T03:34:19.598Z","count":7},{"server":"PvE","player":"Luteanddrum","plus":[],"stats":["cha"],"category":"necklace","text":"CHA necklace","seen":"2026-07-09T03:29:54.054Z","lastSeen":"2026-07-09T03:29:54.054Z","count":1},{"server":"PvE","player":"Gembit","plus":[],"stats":["str","dex"],"category":"jewelry","text":"plat jewelry (7/7) pst for stock/prices (no str/dex in stock atm)","seen":"2026-07-09T03:34:19.598Z","lastSeen":"2026-07-09T03:34:19.598Z","count":1},{"server":"PvP","player":"Hokuto","plus":[],"stats":[],"category":"ring","text":"trading or buying Stirring stick pst","seen":"2026-07-09T03:40:59.479Z","lastSeen":"2026-07-09T03:47:37.222Z","count":4},{"server":"PvP","player":"Vynn","plus":[],"stats":["sta","wis"],"category":null,"text":"7/7 STA WIS jewels","seen":"2026-07-09T03:43:11.510Z","lastSeen":"2026-07-09T03:49:50.359Z","count":4},{"server":"PvE","player":"Kosmopolitan","plus":[4],"stats":["cha"],"category":null,"text":"+ 4 Cha mask enchant","seen":"2026-07-09T04:03:02.929Z","lastSeen":"2026-07-09T04:07:26.902Z","count":3},{"server":"PvP","player":"Vicks","plus":[4],"stats":["str","sta","agi","dex","int","wis","cha"],"category":"necklace","text":"+4 Enchants: Bracer 20g(INT/ STA/WIS/STR), Necklace 7g(CHA/INT/WIS), Cloak 7g(AGI/8 CR/CR/MR/PR), Gloves 6g (AGI/DEX/8 CR/ER)","seen":"2026-07-09T04:11:51.239Z","lastSeen":"2026-07-09T04:11:51.239Z","count":1},{"server":"PvP","player":"Workal","plus":[],"stats":[],"category":"weapon","text":"Steel 2h weapon","seen":"2026-07-09T04:25:07.166Z","lastSeen":"2026-07-09T19:28:37.838Z","count":7},{"server":"PvP","player":"Idylll","plus":[],"stats":[],"category":"weapon","text":"**** rogue dagger\" W orkal auctions, \"WTB Steel 2h weapon","seen":"2026-07-09T04:27:20.196Z","lastSeen":"2026-07-09T04:27:20.196Z","count":1},{"server":"PvP","player":"Boomba","plus":[],"stats":[],"category":"gear","text":"high end gear, link me what you have and tell me what you're looking for","seen":"2026-07-09T04:47:06.598Z","lastSeen":"2026-07-09T04:53:42.950Z","count":4},{"server":"PvE","player":"Worl","plus":[],"stats":[],"category":"ring","text":"Filthstrider or Trailboots, Mercernary's Hood or Infernal Helm, Stalkers Leather Britches, Stirring Stick 80g, Mother's Sorrow 2.5p obo","seen":"2026-07-09T04:49:18.318Z","lastSeen":"2026-07-09T04:49:18.318Z","count":1},{"server":"PvE","player":"Consoom","plus":[],"stats":[],"category":"shield","text":"shaman usable shield, offhand","seen":"2026-07-09T04:51:31.054Z","lastSeen":"2026-07-09T04:53:42.950Z","count":2},{"server":"PvP","player":"Svetlana","plus":[],"stats":["sta"],"category":null,"text":"Bard boots with STA","seen":"2026-07-09T05:19:59.686Z","lastSeen":"2026-07-09T05:26:34.482Z","count":4},{"server":"PvP","player":"Ross","plus":[],"stats":["cha"],"category":null,"text":"cha neck","seen":"2026-07-09T05:22:12.102Z","lastSeen":"2026-07-09T05:28:45.366Z","count":4},{"server":"PvE","player":"Meek","plus":[],"stats":["int"],"category":"gear","text":"int caster gear (necro) wrist, waist, and back","seen":"2026-07-09T05:22:12.102Z","lastSeen":"2026-07-09T05:30:56.886Z","count":5},{"server":"PvE","player":"Pallladin","plus":[],"stats":[],"category":"jewelry","text":"LTB affordable +wisdom jewelry please.","seen":"2026-07-09T05:24:22.878Z","lastSeen":"2026-07-09T05:26:34.482Z","count":2},{"server":"PvE","player":"Darkmoon","plus":[],"stats":[],"category":"ring","text":"The Stirring Stick","seen":"2026-07-09T05:44:07.951Z","lastSeen":"2026-07-09T05:44:07.951Z","count":1},{"server":"PvP","player":"Ross","plus":[],"stats":["cha"],"category":"ring","text":"cha neck/rings","seen":"2026-07-09T05:50:46.598Z","lastSeen":"2026-07-09T05:52:57.862Z","count":2},{"server":"PvP","player":"Koss","plus":[],"stats":["cha"],"category":"ring","text":"cha neck/rings","seen":"2026-07-09T05:55:10.095Z","lastSeen":"2026-07-09T05:55:10.095Z","count":1},{"server":"PvP","player":"Shamlow","plus":[],"stats":[],"category":"gear","text":"Anyone got some cheap hand me down gear for a newbie cleric?","seen":"2026-07-09T06:08:28.486Z","lastSeen":"2026-07-09T06:15:05.182Z","count":4},{"server":"PvE","player":"Ybb","plus":[],"stats":[],"category":"gear","text":"come on now where is the big boy gear for sell?","seen":"2026-07-09T06:10:40.630Z","lastSeen":"2026-07-09T06:12:53.040Z","count":2},{"server":"PvP","player":"Shamlow","plus":[],"stats":[],"category":"gear","text":"Anyone got some cheap hand me down gear tor a newbie cleric?","seen":"2026-07-09T06:17:18.806Z","lastSeen":"2026-07-09T06:17:18.806Z","count":1},{"server":"PvP","player":"Healmage","plus":[],"stats":[],"category":"gear","text":"Cleric gear, lets see it.","seen":"2026-07-09T06:39:31.933Z","lastSeen":"2026-07-09T06:44:01.051Z","count":3},{"server":"PvP","player":"Idylll","plus":[],"stats":["str","dex"],"category":null,"text":"Any JC out there willing to craft some 7/7 STR/DEX sets for 50g each?","seen":"2026-07-09T07:17:24.196Z","lastSeen":"2026-07-09T07:28:25.765Z","count":6},{"server":"PvE","player":"Faithwarden","plus":[],"stats":[],"category":"jewelry","text":"LTB wisdom jewelry","seen":"2026-07-09T07:34:59.214Z","lastSeen":"2026-07-09T07:39:23.950Z","count":3},{"server":"PvP","player":"Surefall","plus":[],"stats":[],"category":"armor","text":"high end Plate Armor and high End Shield","seen":"2026-07-09T07:37:12.542Z","lastSeen":"2026-07-09T07:56:59.990Z","count":10},{"server":"PvE","player":"Aequitasium","plus":[],"stats":["wis"],"category":"gear","text":"cheap +wis leather gear. pst","seen":"2026-07-09T07:59:13.216Z","lastSeen":"2026-07-09T09:07:47.230Z","count":32},{"server":"PvE","player":"Aequitasium","plus":[],"stats":["wis"],"category":"gear","text":"lowbie +wis leather gear, pst","seen":"2026-07-09T08:05:52.019Z","lastSeen":"2026-07-09T09:14:26.438Z","count":32},{"server":"PvP","player":"Sinmage","plus":[],"stats":[],"category":"gear","text":"T1 trash gear to D/E or T1 crystallized magic","seen":"2026-07-09T10:00:43.935Z","lastSeen":"2026-07-09T10:22:33.454Z","count":11},{"server":"PvP","player":"Helianthus","plus":[],"stats":[],"category":"ring","text":"any earing for sale","seen":"2026-07-09T10:16:00.910Z","lastSeen":"2026-07-09T10:35:45.446Z","count":10},{"server":"PvE","player":"Stakilm","plus":[],"stats":[],"category":"armor","text":"Elementalist armor","seen":"2026-07-09T10:29:08.102Z","lastSeen":"2026-07-09T10:31:20.206Z","count":2},{"server":"PvE","player":"Goodgirl","plus":[7],"stats":["str","agi"],"category":"ring","text":"+7 str/agi ring pst","seen":"2026-07-09T10:40:09.762Z","lastSeen":"2026-07-09T11:28:21.486Z","count":23},{"server":"PvP","player":"Idylll","plus":[],"stats":[],"category":"jewelcraft","text":"Any Jewelcrafters on for 7/7 Set?","seen":"2026-07-09T11:02:07.478Z","lastSeen":"2026-07-09T11:30:33.383Z","count":10},{"server":"PvE","player":"Skyark","plus":[],"stats":[],"category":"jeweler","text":"Any jewelers online?","seen":"2026-07-09T11:06:29.376Z","lastSeen":"2026-07-09T11:34:56.566Z","count":14},{"server":"PvP","player":"Idyll","plus":[],"stats":[],"category":"jewelcraft","text":"Any Jewelcrafters on for 7/7 Set?","seen":"2026-07-09T11:15:10.882Z","lastSeen":"2026-07-09T11:28:21.486Z","count":4},{"server":"PvE","player":"Zar","plus":[],"stats":[],"category":"ring","text":"anyone able to make low level ring enchants?","seen":"2026-07-09T11:52:36.393Z","lastSeen":"2026-07-09T11:54:49.469Z","count":2},{"server":"PvE","player":"Primax","plus":[],"stats":[],"category":"weapon","text":"Steel weapons","seen":"2026-07-09T12:12:35.318Z","lastSeen":"2026-07-09T12:21:22.266Z","count":5},{"server":"PvP","player":"Hokuto","plus":[],"stats":[],"category":"ring","text":"or Trade for Stirring stick , pst","seen":"2026-07-09T12:23:34.358Z","lastSeen":"2026-07-09T12:43:28.966Z","count":10},{"server":"PvE","player":"Clouds","plus":[],"stats":["regen"],"category":null,"text":"donating well for greater or exceptional regen :)","seen":"2026-07-09T12:34:35.862Z","lastSeen":"2026-07-09T12:36:48.550Z","count":2},{"server":"PvE","player":"Bbob","plus":[],"stats":["dex","int"],"category":"ring","text":"INT/Dex Rings and Earings","seen":"2026-07-09T12:52:20.732Z","lastSeen":"2026-07-09T12:58:56.822Z","count":4},{"server":"PvP","player":"Fearow","plus":[],"stats":["sta"],"category":null,"text":"Wisdom/Sta Chest piece","seen":"2026-07-09T13:12:09.911Z","lastSeen":"2026-07-09T13:14:21.433Z","count":2},{"server":"PvE","player":"Goron","plus":[],"stats":[],"category":"jewelry","text":"Making 7/7 platinum jewelry, your matts + tip, otherwise selling it pst","seen":"2026-07-09T13:25:23.980Z","lastSeen":"2026-07-09T13:34:15.438Z","count":5},{"server":"PvP","player":"Fearow","plus":[],"stats":["sta"],"category":null,"text":"Wisdom/Sta ChestPiece","seen":"2026-07-09T13:29:50.878Z","lastSeen":"2026-07-09T14:05:01.598Z","count":13},{"server":"PvP","player":"Esoderic","plus":[3,4],"stats":["str"],"category":null,"text":"+3 or +4 str enchant for bracers, legs and shoulders","seen":"2026-07-09T13:32:03.598Z","lastSeen":"2026-07-09T14:22:38.598Z","count":24},{"server":"PvP","player":"Fearow","plus":[],"stats":["sta"],"category":null,"text":"W/TB Wisdom/Sta ChestPiece","seen":"2026-07-09T13:45:13.478Z","lastSeen":"2026-07-09T13:58:26.390Z","count":4},{"server":"PvE","player":"Obimonk","plus":[5],"stats":["str","dex"],"category":"ring","text":"+5 str/dex rings pst with price","seen":"2026-07-09T14:00:38.486Z","lastSeen":"2026-07-09T14:07:14.070Z","count":4},{"server":"PvP","player":"Fearow","plus":[],"stats":["sta"],"category":null,"text":"\"TB Wisdom/Sta ChestPiece","seen":"2026-07-09T14:07:14.070Z","lastSeen":"2026-07-09T14:07:14.070Z","count":1},{"server":"PvE","player":"Aequitasium","plus":[],"stats":["wis"],"category":"gear","text":"leather +wis gear, pst","seen":"2026-07-09T14:16:03.694Z","lastSeen":"2026-07-09T14:18:14.678Z","count":2},{"server":"PvP","player":"Streetmoney","plus":[],"stats":["int"],"category":"gear","text":"wiz/int gear shirt/face/pants/belt/shoes","seen":"2026-07-09T14:35:56.493Z","lastSeen":"2026-07-09T15:43:04.196Z","count":60},{"server":"PvE","player":"Stonka","plus":[],"stats":[],"category":"ring","text":"Mothers Sorrow - Fell Trident - Viper Chain Tunic - The Stirring Stick - Dark Harvest - PST","seen":"2026-07-09T14:46:57.899Z","lastSeen":"2026-07-09T14:49:15.040Z","count":2},{"server":"PvE","player":"Skyark","plus":[7],"stats":["str","dex"],"category":"jewelry","text":"+7 dex/str jewelry","seen":"2026-07-09T14:49:15.040Z","lastSeen":"2026-07-09T14:53:41.462Z","count":3},{"server":"PvE","player":"Skyark","plus":[],"stats":[],"category":"gear","text":"Ranger gear","seen":"2026-07-09T14:55:55.012Z","lastSeen":"2026-07-09T15:00:21.390Z","count":3},{"server":"PvP","player":"Muddy","plus":[],"stats":["str","dex"],"category":"gear","text":"str/dex arc gear chest face shoulder rings","seen":"2026-07-09T15:00:21.390Z","lastSeen":"2026-07-09T15:07:02.006Z","count":4},{"server":"PvE","player":"Dutchess","plus":[],"stats":[],"category":"ring","text":"Bloodied Allengance Cuff or Dirty Pirate Earing","seen":"2026-07-09T15:02:35.166Z","lastSeen":"2026-07-09T15:04:48.534Z","count":2},{"server":"PvE","player":"Stakilm","plus":[],"stats":[],"category":"ring","text":"various lowbie Ele things: Gloves/Mask/wrist(s)/rings/back","seen":"2026-07-09T15:07:02.006Z","lastSeen":"2026-07-09T15:09:15.683Z","count":2},{"server":"PvP","player":"Muddy","plus":[],"stats":["str","dex"],"category":"gear","text":"str/dex archer gear chest/shoulders/face/rings","seen":"2026-07-09T15:09:15.683Z","lastSeen":"2026-07-09T15:20:31.931Z","count":6},{"server":"PvE","player":"Obimonk","plus":[5],"stats":["dex"],"category":"ring","text":"+5str/dex rings pst with price","seen":"2026-07-09T15:20:31.931Z","lastSeen":"2026-07-09T15:22:46.430Z","count":2},{"server":"PvP","player":"Vicks","plus":[],"stats":[],"category":"ring","text":"Magebloom/Whispering Sage/Ironroot/Nomads Grace","seen":"2026-07-09T15:22:46.430Z","lastSeen":"2026-07-09T15:27:16.767Z","count":4},{"server":"PvE","player":"Caele","plus":[],"stats":[],"category":"ring","text":"Tipping for tailoring services. Need Wool Padding made","seen":"2026-07-09T15:29:32.505Z","lastSeen":"2026-07-09T15:29:32.505Z","count":1},{"server":"PvP","player":"Muddy","plus":[],"stats":["str","dex"],"category":"gear","text":"str/dex arc gear shoulders/chest/face/rings","seen":"2026-07-09T15:31:48.358Z","lastSeen":"2026-07-09T15:40:48.694Z","count":5},{"server":"PvP","player":"Muddy","plus":[],"stats":["str","dex"],"category":"gear","text":"str/dex arch gear chest/shoulders/rings/face","seen":"2026-07-09T15:45:18.318Z","lastSeen":"2026-07-09T16:09:58.598Z","count":12},{"server":"PvE","player":"Clouds","plus":[],"stats":["regen"],"category":null,"text":"tipping 30s for exceptional or greater regen + buffs pst :)","seen":"2026-07-09T15:56:31.694Z","lastSeen":"2026-07-09T15:56:31.694Z","count":1},{"server":"PvE","player":"Ontble","plus":[],"stats":[],"category":"weapon","text":"oh boy i just gave one to my pet for weapon sorry guys","seen":"2026-07-09T16:01:01.429Z","lastSeen":"2026-07-09T16:01:01.429Z","count":1},{"server":"PvP","player":"Ross","plus":[],"stats":["cha"],"category":"ring","text":"cha ring/neck","seen":"2026-07-09T16:09:58.598Z","lastSeen":"2026-07-09T16:16:41.270Z","count":4},{"server":"PvE","player":"Clouds","plus":[],"stats":["regen"],"category":null,"text":"donating 30s for exceptional or greater regen pst :)","seen":"2026-07-09T16:09:58.598Z","lastSeen":"2026-07-09T16:25:40.196Z","count":3},{"server":"PvP","player":"Hyperwig","plus":[],"stats":["int","cha"],"category":"gear","text":"Cha/Int Gear Chest, Back Shoulders PST stats/price","seen":"2026-07-09T16:14:27.094Z","lastSeen":"2026-07-09T16:23:25.411Z","count":5},{"server":"PvE","player":"Clouds","plus":[],"stats":["regen"],"category":null,"text":"donating with intense passion for greater or exceptional regen","seen":"2026-07-09T16:14:27.094Z","lastSeen":"2026-07-09T16:16:41.270Z","count":2},{"server":"PvP","player":"Hyperwig","plus":[],"stats":["int","cha"],"category":"gear","text":"Cha/Int gear Chest Shoulders Back PST stats/price","seen":"2026-07-09T16:21:10.870Z","lastSeen":"2026-07-09T16:25:40.196Z","count":3},{"server":"PvP","player":"Kissinmen","plus":[],"stats":["int"],"category":null,"text":"Wiz int helm/legs/bracers/gloves/cape/face","seen":"2026-07-09T16:27:54.008Z","lastSeen":"2026-07-09T16:36:50.460Z","count":5},{"server":"PvP","player":"Southern","plus":[],"stats":["int","cha"],"category":"gear","text":"Cha/Int Gear Chest Back Shoulders PST stats/price","seen":"2026-07-09T16:30:07.576Z","lastSeen":"2026-07-09T16:41:19.190Z","count":6},{"server":"PvP","player":"Southern","plus":[],"stats":["int","cha"],"category":"gear","text":"Int/Cha Gear Chest Back Shoulders PST prices/stats","seen":"2026-07-09T16:39:04.770Z","lastSeen":"2026-07-09T16:48:02.798Z","count":5},{"server":"PvP","player":"Kissinmen","plus":[],"stats":["int"],"category":null,"text":"Wiz int legs/bracers/gloves/cape/face","seen":"2026-07-09T16:43:33.581Z","lastSeen":"2026-07-09T16:48:02.798Z","count":3},{"server":"PvP","player":"Vicks","plus":[],"stats":[],"category":"ring","text":"Magebloom/Shadeshroom/ Whispering Sage/Ironroot/Nomads Grace","seen":"2026-07-09T16:50:17.814Z","lastSeen":"2026-07-09T22:15:22.942Z","count":2},{"server":"PvE","player":"Sonadar","plus":[7],"stats":["str","agi"],"category":"ring","text":"+7 STR/AGI Earrings and necklace","seen":"2026-07-09T16:59:09.270Z","lastSeen":"2026-07-09T17:23:47.041Z","count":2},{"server":"PvE","player":"Bokx","plus":[11],"stats":["str"],"category":null,"text":"+11 str sharpenings stones plz - pst","seen":"2026-07-09T17:01:23.670Z","lastSeen":"2026-07-09T17:01:23.670Z","count":1},{"server":"PvP","player":"Vicks","plus":[],"stats":["resist"],"category":null,"text":"Shoulder 14g (UEX/S1K/8 any resist), Leg 14g (SLA/S1R/8 any resist)","seen":"2026-07-09T17:12:33.078Z","lastSeen":"2026-07-09T17:12:33.078Z","count":1},{"server":"PvP","player":"Vicks","plus":[],"stats":["resist"],"category":null,"text":"Shoulder 14g (UEX/S1K/8 any resist), Leg 14g (SL A/S1K/8 any resist)","seen":"2026-07-09T17:14:48.470Z","lastSeen":"2026-07-09T17:14:48.470Z","count":1},{"server":"PvE","player":"Clouds","plus":[],"stats":["regen"],"category":null,"text":"tipping 30s for exceptional or greater regen pst","seen":"2026-07-09T17:46:01.174Z","lastSeen":"2026-07-09T17:46:01.174Z","count":1},{"server":"PvE","player":"Meek","plus":[],"stats":["int"],"category":null,"text":"int caster (necro) waist, wrist, and back!","seen":"2026-07-09T17:50:25.934Z","lastSeen":"2026-07-09T18:10:18.506Z","count":5},{"server":"PvP","player":"Boisterous","plus":[],"stats":[],"category":"weapon","text":"steel 1h weapon","seen":"2026-07-09T17:57:01.272Z","lastSeen":"2026-07-09T18:03:40.196Z","count":4},{"server":"PvP","player":"Moraxus","plus":[],"stats":["str"],"category":null,"text":"str chestpiece","seen":"2026-07-09T18:03:40.196Z","lastSeen":"2026-07-09T18:19:08.102Z","count":8},{"server":"PvP","player":"Moraxus","plus":[],"stats":["str","ac"],"category":null,"text":"str chestpiece 7g (pref plate, high ac)","seen":"2026-07-09T18:05:52.926Z","lastSeen":"2026-07-09T18:23:33.078Z","count":4},{"server":"PvP","player":"Moraxus","plus":[],"stats":["str","ac"],"category":null,"text":"str chestpiece 7¢ (pref plate, high ac)","seen":"2026-07-09T18:08:05.847Z","lastSeen":"2026-07-09T18:19:08.102Z","count":5},{"server":"PvE","player":"Trainz","plus":[7],"stats":["dex"],"category":"ring","text":"+7STR/DEX rings+earrings.","seen":"2026-07-09T18:12:31.296Z","lastSeen":"2026-07-09T18:14:43.769Z","count":2},{"server":"PvE","player":"Jumbo","plus":[],"stats":["str","dex"],"category":"ring","text":"3 dex/str earrings and rings","seen":"2026-07-09T18:14:43.769Z","lastSeen":"2026-07-09T18:14:43.769Z","count":1},{"server":"PvE","player":"Trainz","plus":[7],"stats":["dex"],"category":"ring","text":"W/TB +7STR/DEX rings+earrings.","seen":"2026-07-09T18:28:01.770Z","lastSeen":"2026-07-09T18:28:01.770Z","count":1},{"server":"PvE","player":"Elcid","plus":[],"stats":["dex","cha"],"category":null,"text":"Greater Cha Face, Greater Dex enchants","seen":"2026-07-09T18:28:01.770Z","lastSeen":"2026-07-09T18:39:11.481Z","count":3},{"server":"PvE","player":"Jart","plus":[],"stats":["wis"],"category":"jewelry","text":"Wis/Charisma jewelry","seen":"2026-07-09T18:34:43.838Z","lastSeen":"2026-07-09T18:34:43.838Z","count":1},{"server":"PvE","player":"Elcid","plus":[],"stats":["str"],"category":null,"text":"Greater Str belt","seen":"2026-07-09T18:39:11.481Z","lastSeen":"2026-07-09T18:39:11.481Z","count":1},{"server":"PvE","player":"Jart","plus":[5],"stats":[],"category":"jewelry","text":"+5Wis/Charisma jewelry","seen":"2026-07-09T18:41:25.078Z","lastSeen":"2026-07-09T18:41:25.078Z","count":1},{"server":"PvP","player":"Getafix","plus":[],"stats":["str"],"category":null,"text":"honestly two wolfclaws is prety nice, that STR is crazy good","seen":"2026-07-09T18:48:06.452Z","lastSeen":"2026-07-09T18:54:48.472Z","count":4},{"server":"PvE","player":"Enchantresse","plus":[],"stats":["int","cha"],"category":"jewelry","text":"5 int/cha jewelry","seen":"2026-07-09T18:59:17.521Z","lastSeen":"2026-07-09T19:06:02.294Z","count":3},{"server":"PvE","player":"Foulo","plus":[],"stats":[],"category":"jewelry","text":"Foulo 7/7 jewelcrafting service crafting any platinium jewelry if you provide the gem 1g for an earring 1.5g for a ring or a necklace","seen":"2026-07-09T19:15:03.959Z","lastSeen":"2026-07-09T19:15:03.959Z","count":1},{"server":"PvE","player":"Foulo","plus":[],"stats":[],"category":"jewelry","text":"7/7 jewelcrafting service crafting any platinium jewelry if you provide the gem 1g for an earring 1.5g for a ring or a necklace","seen":"2026-07-09T19:17:19.430Z","lastSeen":"2026-07-09T20:26:40.398Z","count":19},{"server":"PvE","player":"Dutchess","plus":[],"stats":["sta","int"],"category":null,"text":"+STA or + INT, Neck Chest or Legs enchant PST","seen":"2026-07-09T19:21:51.574Z","lastSeen":"2026-07-09T19:21:51.574Z","count":1},{"server":"PvE","player":"Bulini","plus":[7],"stats":[],"category":"jewelery","text":"Platinum Jewelery (+7/+7) have all gems, discounts on full sets.","seen":"2026-07-09T19:26:21.762Z","lastSeen":"2026-07-09T19:26:21.762Z","count":1},{"server":"PvE","player":"Lanius","plus":[],"stats":[],"category":"jewelcraft","text":"LF silver capable jewelcrafter - have gems","seen":"2026-07-09T19:28:37.838Z","lastSeen":"2026-07-09T19:48:40.438Z","count":5},{"server":"PvE","player":"Enchantresse","plus":[],"stats":["int","cha"],"category":"jewelry","text":"5 int/cha jewelry!","seen":"2026-07-09T19:28:37.838Z","lastSeen":"2026-07-09T19:39:47.412Z","count":2},{"server":"PvP","player":"Saucy","plus":[],"stats":["int"],"category":null,"text":"+INT legs\\waist\\face","seen":"2026-07-09T19:37:33.366Z","lastSeen":"2026-07-09T19:42:01.414Z","count":3},{"server":"PvP","player":"Ebola","plus":[],"stats":[],"category":"gear","text":"high end SPB gear, jewelry","seen":"2026-07-09T20:08:41.518Z","lastSeen":"2026-07-09T20:10:56.222Z","count":2},{"server":"PvE","player":"Foulo","plus":[],"stats":[],"category":"jewelry","text":"7/7 jewelcrafting service crafting any platinium jewelry if you provide the gem (a lot are on the miner vendor) 1g for an earring 1.5g for a ring or a necklace","seen":"2026-07-09T20:13:12.998Z","lastSeen":"2026-07-09T20:22:11.598Z","count":4},{"server":"PvP","player":"Perplexer","plus":[],"stats":["int"],"category":null,"text":"necro Int or Int/Stam Face, Cloak, Wrists, Range, Belt","seen":"2026-07-09T20:19:57.040Z","lastSeen":"2026-07-10T00:51:47.938Z","count":4},{"server":"PvP","player":"Littlejimmy","plus":[],"stats":[],"category":"armour","text":"Jimmy's armoury is located near food outlets, accessible parking","seen":"2026-07-09T20:22:11.598Z","lastSeen":"2026-07-09T20:24:26.286Z","count":2},{"server":"PvE","player":"Shaake","plus":[],"stats":["str"],"category":null,"text":"nub str pants/shoulders/gloves/face.....at walmart prices please","seen":"2026-07-09T20:24:26.286Z","lastSeen":"2026-07-09T20:24:26.286Z","count":1},{"server":"PvE","player":"Enchantresse","plus":[5],"stats":["cha"],"category":"jewelry","text":"+5int/cha jewelry!","seen":"2026-07-09T20:28:53.502Z","lastSeen":"2026-07-09T20:28:53.502Z","count":1},{"server":"PvP","player":"Idyll","plus":[],"stats":["str","dex"],"category":"jewelery","text":"STR/DEX Jewelery and Rogue items. WTB Cloth Scrap","seen":"2026-07-09T20:33:20.598Z","lastSeen":"2026-07-09T20:33:20.598Z","count":1},{"server":"PvE","player":"Foulo","plus":[],"stats":[],"category":"jewelry","text":"Foulo's jewelcrafting service crafting any 7/7 platinium jewelry if you provide the gem 1g for an earring 1.5g for a ring or a necklace","seen":"2026-07-09T20:33:20.598Z","lastSeen":"2026-07-10T02:11:27.358Z","count":73},{"server":"PvE","player":"Enchantresse","plus":[5],"stats":["int","cha"],"category":"jewelry","text":"+5 int/cha jewelry set!","seen":"2026-07-09T20:37:48.773Z","lastSeen":"2026-07-09T22:39:40.465Z","count":9},{"server":"PvE","player":"Stonka","plus":[],"stats":[],"category":"ring","text":"Viper Tunic / Fell Trident / Stirring Stick / Filthstriders PST","seen":"2026-07-09T20:57:49.199Z","lastSeen":"2026-07-09T21:04:31.102Z","count":2},{"server":"PvP","player":"Vynn","plus":[],"stats":["sta","wis"],"category":null,"text":"7/7 sta/wis jewels","seen":"2026-07-09T21:02:17.513Z","lastSeen":"2026-07-09T21:15:34.459Z","count":7},{"server":"PvE","player":"Wulfrack","plus":[],"stats":["cha"],"category":"gear","text":"Cha gear","seen":"2026-07-09T21:02:17.513Z","lastSeen":"2026-07-09T21:02:17.513Z","count":1},{"server":"PvE","player":"Wulfrack","plus":[],"stats":["cha"],"category":"gear","text":"cha gear, jewlery","seen":"2026-07-09T21:04:31.102Z","lastSeen":"2026-07-09T21:04:31.102Z","count":1},{"server":"PvP","player":"Idylll","plus":[],"stats":[],"category":"jewelry","text":"7/7 Jewelry can pay for whole set","seen":"2026-07-09T21:22:16.406Z","lastSeen":"2026-07-09T21:22:16.406Z","count":1},{"server":"PvE","player":"Kalamar","plus":[],"stats":[],"category":"gear","text":"cheap/newbie gnome wizard gear 1g max per slot","seen":"2026-07-09T21:22:16.406Z","lastSeen":"2026-07-09T21:22:16.406Z","count":1},{"server":"PvP","player":"Idyll","plus":[],"stats":["str","dex"],"category":"gear","text":"STR/Dex Gear /Jewelery","seen":"2026-07-09T21:26:43.686Z","lastSeen":"2026-07-09T21:33:18.486Z","count":2},{"server":"PvP","player":"Idylll","plus":[],"stats":["str","dex"],"category":"gear","text":"STR/Dex Gear /Jewelery","seen":"2026-07-09T21:28:55.390Z","lastSeen":"2026-07-09T21:31:07.030Z","count":2},{"server":"PvP","player":"Urmom","plus":[],"stats":["str"],"category":null,"text":"W/TB STR LEATHER LEGS / CHEST","seen":"2026-07-09T21:35:30.323Z","lastSeen":"2026-07-09T21:35:30.323Z","count":1},{"server":"PvP","player":"Urmom","plus":[],"stats":["str"],"category":null,"text":"TB STR LEATHER LEGS / CHEST","seen":"2026-07-09T21:37:43.313Z","lastSeen":"2026-07-09T21:37:43.313Z","count":1},{"server":"PvP","player":"Urmom","plus":[],"stats":["str"],"category":null,"text":"STR LEATHER LEGS / CHEST","seen":"2026-07-09T21:39:55.678Z","lastSeen":"2026-07-09T21:39:55.678Z","count":1},{"server":"PvP","player":"Urmom","plus":[],"stats":["str"],"category":null,"text":"\"/TB STR LEATHER LEGS / CHEST","seen":"2026-07-09T21:42:10.452Z","lastSeen":"2026-07-09T21:42:10.452Z","count":1},{"server":"PvE","player":"Marlboroman","plus":[],"stats":[],"category":"weapon","text":"cleric weapon, best i can get with a 50s budget","seen":"2026-07-09T21:42:10.452Z","lastSeen":"2026-07-09T21:44:22.777Z","count":2},{"server":"PvP","player":"Urmom","plus":[],"stats":["str"],"category":null,"text":"STR leather LEGS / CHEST / HELM","seen":"2026-07-09T21:44:22.777Z","lastSeen":"2026-07-09T21:57:38.350Z","count":7},{"server":"PvP","player":"Figgie","plus":[],"stats":["sta","int"],"category":null,"text":"7/7 sta/int set","seen":"2026-07-09T21:48:47.934Z","lastSeen":"2026-07-09T21:59:50.846Z","count":6},{"server":"PvE","player":"Marlboroman","plus":[],"stats":[],"category":"weapon","text":"cleric weapon, steel mace/hammer or better (50s budget)","seen":"2026-07-09T21:53:12.438Z","lastSeen":"2026-07-09T21:53:12.438Z","count":1},{"server":"PvE","player":"Talobar","plus":[],"stats":["cha"],"category":null,"text":"Cha enchantment for head","seen":"2026-07-09T21:53:12.438Z","lastSeen":"2026-07-09T21:53:12.438Z","count":1},{"server":"PvE","player":"Sonadar","plus":[7],"stats":["str","sta"],"category":null,"text":"STR+7 STA+7 3g","seen":"2026-07-09T21:57:38.350Z","lastSeen":"2026-07-09T22:04:16.785Z","count":4},{"server":"PvP","player":"Kissinmen","plus":[],"stats":["int"],"category":null,"text":"Wiz int bracers/legs/gloves/cape/face/neck","seen":"2026-07-09T22:10:56.214Z","lastSeen":"2026-07-09T22:35:16.334Z","count":11},{"server":"PvP","player":"Vicks","plus":[],"stats":[],"category":"ring","text":"Magebloom/Shadeshroom/Whispering Sage/Ironroot/Nomads Grace","seen":"2026-07-09T22:10:56.214Z","lastSeen":"2026-07-09T22:17:37.238Z","count":3},{"server":"PvP","player":"Vicks","plus":[],"stats":[],"category":"ring","text":"Magebloom/Shadeshroom/ Whispering Sage/Ironroot/Nomads Grace/Carrion Beetle Eyes/Phantom Residue","seen":"2026-07-09T22:13:09.878Z","lastSeen":"2026-07-10T04:21:44.454Z","count":6},{"server":"PvP","player":"Vicks","plus":[],"stats":[],"category":"ring","text":"Magebloom/Shadeshroom/Whispering Sage/Ironroot/Nomads Grace/Carrion Beetle Eyes/Phantom Residue","seen":"2026-07-09T22:15:22.942Z","lastSeen":"2026-07-10T04:43:45.686Z","count":18},{"server":"PvE","player":"Araxis","plus":[],"stats":[],"category":"gear","text":"Newbie wizard gear","seen":"2026-07-09T22:17:37.238Z","lastSeen":"2026-07-09T22:17:37.238Z","count":2},{"server":"PvE","player":"Force","plus":[],"stats":["wis"],"category":"ring","text":"low end wis rings/earrings/glove/wrist/back/shoulder","seen":"2026-07-09T22:17:37.238Z","lastSeen":"2026-07-09T22:17:37.238Z","count":1},{"server":"PvP","player":"Kalamon","plus":[],"stats":["wis","cha"],"category":"jewelry","text":"wis/cha jewelry","seen":"2026-07-09T22:28:39.588Z","lastSeen":"2026-07-09T22:41:51.222Z","count":7},{"server":"PvE","player":"Bushwacker","plus":[],"stats":["str","dex"],"category":"jewelry","text":"Str/Dex Jewelry Pst","seen":"2026-07-09T22:35:16.334Z","lastSeen":"2026-07-09T22:35:16.334Z","count":1},{"server":"PvE","player":"Xibat","plus":[],"stats":[],"category":"gear","text":"Ranger Gear - Head, Shoulders, Face & Wrists PST","seen":"2026-07-09T22:44:01.814Z","lastSeen":"2026-07-09T22:44:01.814Z","count":1},{"server":"PvE","player":"Xibat","plus":[],"stats":[],"category":"gear","text":"Ranger Gear - Head, Shoulders, Face, Belt & Wrists PST","seen":"2026-07-09T22:46:12.995Z","lastSeen":"2026-07-09T23:19:19.198Z","count":6},{"server":"PvE","player":"Asrod","plus":[],"stats":["haste"],"category":null,"text":"i got haste","seen":"2026-07-09T22:48:25.783Z","lastSeen":"2026-07-09T22:48:25.783Z","count":1},{"server":"PvE","player":"Convikt","plus":[],"stats":["wis"],"category":"armor","text":"lookin for low level plate armor with wis","seen":"2026-07-09T22:48:25.783Z","lastSeen":"2026-07-09T22:50:37.564Z","count":2},{"server":"PvE","player":"Xeanas","plus":[],"stats":[],"category":"necklace","text":"a blue sapphire necklace","seen":"2026-07-09T22:52:50.822Z","lastSeen":"2026-07-09T22:52:50.822Z","count":1},{"server":"PvE","player":"Xeanas","plus":[],"stats":[],"category":"necklace","text":"i have the blue sapphire to use for the necklace","seen":"2026-07-09T22:52:50.822Z","lastSeen":"2026-07-09T22:52:50.822Z","count":1},{"server":"PvE","player":"Faithwarden","plus":[],"stats":[],"category":"ring","text":"LTB Inlaid Jasper earrings & necklace <3","seen":"2026-07-09T22:52:50.822Z","lastSeen":"2026-07-09T22:52:50.822Z","count":1},{"server":"PvE","player":"Twoinchesofpain","plus":[],"stats":[],"category":"weapon","text":"/TB Cheap monk weapons.","seen":"2026-07-09T22:55:02.785Z","lastSeen":"2026-07-09T22:55:02.785Z","count":1},{"server":"PvE","player":"Faithwarden","plus":[2],"stats":["mana"],"category":"ring","text":"LTB +2 jasper wisdom mana necklace and earrings","seen":"2026-07-09T22:59:26.262Z","lastSeen":"2026-07-09T22:59:26.262Z","count":1},{"server":"PvP","player":"Rodnee","plus":[],"stats":[],"category":"weapon","text":"2h weapon ~10g PST","seen":"2026-07-09T23:21:30.806Z","lastSeen":"2026-07-09T23:32:29.598Z","count":11},{"server":"PvE","player":"Xibat","plus":[],"stats":[],"category":"gear","text":"Ranger Gear - Shoulders, Face, & Wrists PST","seen":"2026-07-09T23:21:30.806Z","lastSeen":"2026-07-09T23:39:06.342Z","count":5},{"server":"PvE","player":"Stonka","plus":[],"stats":["str"],"category":null,"text":"STR Potions & Weightly Sharpening Stones PST","seen":"2026-07-09T23:25:53.582Z","lastSeen":"2026-07-09T23:25:53.582Z","count":1},{"server":"PvP","player":"Rodnee","plus":[],"stats":[],"category":"weapon","text":"TB 2h weapon ~10g PST","seen":"2026-07-09T23:28:05.234Z","lastSeen":"2026-07-09T23:28:05.234Z","count":1},{"server":"PvP","player":"Muddy","plus":[],"stats":["str","dex"],"category":"gear","text":"str/dex arc gear chest/shoulders/face/rings pst","seen":"2026-07-09T23:28:05.234Z","lastSeen":"2026-07-09T23:32:29.598Z","count":3},{"server":"PvP","player":"Muddy","plus":[],"stats":["str","dex"],"category":"gear","text":"W 15 str/dex arc gear chest/shoulders/tace/rings pst","seen":"2026-07-09T23:34:40.792Z","lastSeen":"2026-07-09T23:34:40.792Z","count":1},{"server":"PvP","player":"Muddy","plus":[],"stats":["str","dex"],"category":"gear","text":"str/dex arc gear chest/shoulder/face/rings pst","seen":"2026-07-09T23:39:06.342Z","lastSeen":"2026-07-10T02:07:01.014Z","count":54},{"server":"PvE","player":"Stonka","plus":[],"stats":["str"],"category":null,"text":"STR Potions & Weightly Weight Stones PST","seen":"2026-07-09T23:39:06.342Z","lastSeen":"2026-07-09T23:39:06.342Z","count":1},{"server":"PvP","player":"Vymm","plus":[],"stats":["sta","wis"],"category":null,"text":"7/7 wis/sta jewels","seen":"2026-07-09T23:41:18.594Z","lastSeen":"2026-07-09T23:43:31.041Z","count":2},{"server":"PvP","player":"Rodnee","plus":[],"stats":[],"category":"weapon","text":"2h weapon ~10g","seen":"2026-07-09T23:41:18.594Z","lastSeen":"2026-07-09T23:45:43.054Z","count":3},{"server":"PvP","player":"Nolletta","plus":[],"stats":["int","cha"],"category":"gear","text":"Int/Cha Gear Chest, Shoulder, Back, Feet PST stats/price","seen":"2026-07-09T23:45:43.054Z","lastSeen":"2026-07-10T04:12:51.911Z","count":22},{"server":"PvE","player":"Xibat","plus":[],"stats":[],"category":"gear","text":"Ranger Gear - Shoulders & Wrists PST","seen":"2026-07-09T23:45:43.054Z","lastSeen":"2026-07-09T23:56:42.102Z","count":2},{"server":"PvP","player":"Rodnee","plus":[],"stats":[],"category":"weapon","text":"2h weapon ~ 10g","seen":"2026-07-09T23:47:55.742Z","lastSeen":"2026-07-09T23:47:55.742Z","count":1},{"server":"PvP","player":"Rodnee","plus":[],"stats":[],"category":"weapon","text":"2h weapon!","seen":"2026-07-09T23:47:55.742Z","lastSeen":"2026-07-09T23:50:08.654Z","count":2},{"server":"PvP","player":"Vine","plus":[],"stats":[],"category":"gear","text":"Archer gear","seen":"2026-07-09T23:50:08.654Z","lastSeen":"2026-07-09T23:54:30.870Z","count":3},{"server":"PvE","player":"Jett","plus":[],"stats":[],"category":"weapon","text":"cheap monk weapon 55 silver price range.","seen":"2026-07-09T23:54:30.870Z","lastSeen":"2026-07-09T23:54:30.870Z","count":1},{"server":"PvP","player":"Rodnee","plus":[],"stats":[],"category":"weapon","text":"2h weapon","seen":"2026-07-10T00:03:17.792Z","lastSeen":"2026-07-10T03:28:43.040Z","count":11},{"server":"PvP","player":"Vanuiil","plus":[],"stats":[],"category":"weapon","text":"2H Weapon SK/BST /tell with Link and Price","seen":"2026-07-10T00:03:17.792Z","lastSeen":"2026-07-10T00:12:03.542Z","count":5},{"server":"PvE","player":"Vendetta","plus":[],"stats":[],"category":"armor","text":"Crafted plate armorset","seen":"2026-07-10T00:03:17.792Z","lastSeen":"2026-07-10T00:03:17.792Z","count":1},{"server":"PvE","player":"Jett","plus":[],"stats":[],"category":"weapon","text":"cheap monk weapons","seen":"2026-07-10T00:05:28.526Z","lastSeen":"2026-07-10T08:43:45.414Z","count":23},{"server":"PvE","player":"Pellios","plus":[],"stats":[],"category":"armour","text":"Any BS that can make Iron or Steel plate armour can you PST me your prices","seen":"2026-07-10T00:05:28.526Z","lastSeen":"2026-07-10T00:05:28.526Z","count":1},{"server":"PvP","player":"Muddy","plus":[],"stats":[],"category":"gear","text":"arc gear chest/shoulder/face/rings pst","seen":"2026-07-10T00:20:53.792Z","lastSeen":"2026-07-10T00:20:53.792Z","count":1},{"server":"PvP","player":"Vine","plus":[],"stats":[],"category":"ring","text":"high end bow for archer, and melee wp, and rings/earrings","seen":"2026-07-10T00:23:07.022Z","lastSeen":"2026-07-10T00:25:17.886Z","count":2},{"server":"PvP","player":"Illusion","plus":[],"stats":[],"category":"weapon","text":"Anyone seeling any strong weapons","seen":"2026-07-10T00:23:07.022Z","lastSeen":"2026-07-10T00:25:17.886Z","count":2},{"server":"PvE","player":"Enchantresse","plus":[5],"stats":["int","cha"],"category":"jewelry","text":"+5 Int/cha jewelry!","seen":"2026-07-10T00:27:30.366Z","lastSeen":"2026-07-10T00:31:55.724Z","count":2},{"server":"PvP","player":"Nolletta","plus":[],"stats":["int","cha"],"category":"gear","text":"TB Int/Cha Gear Chest, Shoulder, Back, Feet PST stats/price","seen":"2026-07-10T00:47:22.598Z","lastSeen":"2026-07-10T03:00:02.327Z","count":3},{"server":"PvP","player":"Hyperwig","plus":[],"stats":["int","cha"],"category":"gear","text":"Int/Cha Gear Chest, Shoulder, Back, Feet PST stats/price","seen":"2026-07-10T00:56:13.230Z","lastSeen":"2026-07-10T05:25:44.807Z","count":61},{"server":"PvE","player":"Stonka","plus":[],"stats":[],"category":"ring","text":"StOnKa WTB - Glass Viper Tunic - Defilers Blade - Stirring Stick - Dark Harvest - Fell Trident - Filthstriders PST","seen":"2026-07-10T00:56:13.230Z","lastSeen":"2026-07-10T01:07:15.390Z","count":2},{"server":"PvP","player":"Idylll","plus":[],"stats":[],"category":"gear","text":"ROG Gear/Cloth Scraps/ Love","seen":"2026-07-10T01:05:03.398Z","lastSeen":"2026-07-10T01:11:39.198Z","count":3},{"server":"PvE","player":"Finneas","plus":[],"stats":[],"category":"gear","text":"low level druid gear","seen":"2026-07-10T01:05:03.398Z","lastSeen":"2026-07-10T01:05:03.398Z","count":1},{"server":"PvP","player":"Idylll","plus":[],"stats":[],"category":"jewelery","text":"Any JC out there WTB 7/7 Set Jewelery 60g","seen":"2026-07-10T01:07:15.390Z","lastSeen":"2026-07-10T01:11:39.198Z","count":3},{"server":"PvP","player":"Idyll","plus":[],"stats":[],"category":"gear","text":"ROG Gear/Cloth Scraps/ Love","seen":"2026-07-10T01:09:26.990Z","lastSeen":"2026-07-10T01:09:26.990Z","count":1},{"server":"PvP","player":"Idylll","plus":[],"stats":[],"category":"jewelery","text":"7/7 Jewelery paying well","seen":"2026-07-10T01:55:57.054Z","lastSeen":"2026-07-10T01:55:57.054Z","count":1},{"server":"PvE","player":"Heavy","plus":[4],"stats":[],"category":"gear","text":"gear Ench +4 pst","seen":"2026-07-10T01:55:57.054Z","lastSeen":"2026-07-10T02:13:40.014Z","count":2},{"server":"PvP","player":"Idylll","plus":[],"stats":["str","agi"],"category":null,"text":"Any JC on? Will pay 40g for 7/7 STR/AGI Set","seen":"2026-07-10T01:58:07.894Z","lastSeen":"2026-07-10T02:00:21.238Z","count":2},{"server":"PvP","player":"Streetmoney","plus":[],"stats":["int"],"category":"gear","text":"wiz/int gear - shirt/pants/belt/face/shoes","seen":"2026-07-10T01:58:07.894Z","lastSeen":"2026-07-10T02:00:21.238Z","count":2},{"server":"PvP","player":"Idylll","plus":[],"stats":["str","agi"],"category":"gear","text":"STR/AGI Gear will pay g and more :O","seen":"2026-07-10T02:00:21.238Z","lastSeen":"2026-07-10T02:00:21.238Z","count":1},{"server":"PvP","player":"Rodnee","plus":[],"stats":[],"category":"weapon","text":"mid-range lvl weapon(s)","seen":"2026-07-10T02:04:47.894Z","lastSeen":"2026-07-10T02:07:01.014Z","count":2},{"server":"PvP","player":"Streetmoney","plus":[],"stats":["int"],"category":"gear","text":"wiz/int gear - face/pants/belt/shoes","seen":"2026-07-10T02:09:13.255Z","lastSeen":"2026-07-10T07:44:34.366Z","count":48},{"server":"PvP","player":"Rodnee","plus":[],"stats":[],"category":"weapon","text":"lvl ~40 weapon(s)","seen":"2026-07-10T02:11:27.358Z","lastSeen":"2026-07-10T02:13:40.014Z","count":2},{"server":"PvP","player":"Muddy","plus":[],"stats":["str","dex"],"category":"gear","text":"str/dex arc gear shoulder/face/rings pst","seen":"2026-07-10T02:11:27.358Z","lastSeen":"2026-07-10T02:13:40.014Z","count":2},{"server":"PvE","player":"Jevayde","plus":[],"stats":["str"],"category":null,"text":"str pots and/or weightstones tier 2+","seen":"2026-07-10T02:11:27.358Z","lastSeen":"2026-07-10T02:11:27.358Z","count":1},{"server":"PvE","player":"Whitemane","plus":[],"stats":[],"category":"ring","text":"6ac 35hp rings","seen":"2026-07-10T02:13:40.014Z","lastSeen":"2026-07-10T02:13:40.014Z","count":1},{"server":"PvP","player":"Idylll","plus":[],"stats":["str","dex"],"category":null,"text":"LF JC to Craft STR/Dex Set 7/7 35g PST","seen":"2026-07-10T02:15:51.062Z","lastSeen":"2026-07-10T02:22:29.247Z","count":4},{"server":"PvP","player":"Idylll","plus":[],"stats":["str","agi"],"category":null,"text":"Sorry STR/AGI","seen":"2026-07-10T02:15:51.062Z","lastSeen":"2026-07-10T02:22:29.247Z","count":4},{"server":"PvE","player":"Meek","plus":[],"stats":["int"],"category":"gear","text":"int caster gear (necro) - wrist, waist, and back.","seen":"2026-07-10T02:20:15.526Z","lastSeen":"2026-07-10T02:24:41.574Z","count":2},{"server":"PvE","player":"Boole","plus":[],"stats":["int"],"category":null,"text":"INT gloves/cape","seen":"2026-07-10T02:24:41.574Z","lastSeen":"2026-07-10T02:24:41.574Z","count":1},{"server":"PvP","player":"Idyll","plus":[],"stats":["str","agi"],"category":null,"text":"7/7 STR/AGI Set paying 40g","seen":"2026-07-10T03:08:47.870Z","lastSeen":"2026-07-10T03:08:47.870Z","count":1},{"server":"PvP","player":"Idylll","plus":[],"stats":["str","agi"],"category":null,"text":"7/7 STR/AGI Set paying 40g","seen":"2026-07-10T03:10:57.238Z","lastSeen":"2026-07-10T03:13:09.178Z","count":2},{"server":"PvE","player":"Arconiann","plus":[],"stats":[],"category":"gear","text":"gear for a Spellblade, I have 2 gold. Need shirt, gloves, back, belt, wrists, face, boots, legs.","seen":"2026-07-10T03:15:22.598Z","lastSeen":"2026-07-10T03:19:50.678Z","count":3},{"server":"PvE","player":"Shanksalot","plus":[],"stats":["str","dex"],"category":"ring","text":"anybody sellin str/dex rings?","seen":"2026-07-10T03:24:18.862Z","lastSeen":"2026-07-10T03:24:18.862Z","count":1},{"server":"PvE","player":"Shanksalot","plus":[],"stats":["str","dex"],"category":"ring","text":"str/dex rings","seen":"2026-07-10T03:26:30.902Z","lastSeen":"2026-07-10T03:57:28.716Z","count":5},{"server":"PvE","player":"Ybba","plus":[],"stats":[],"category":"gear","text":"lvl 30ish necro gear please","seen":"2026-07-10T03:30:55.031Z","lastSeen":"2026-07-10T03:30:55.031Z","count":1},{"server":"PvE","player":"Pandalem","plus":[],"stats":["int"],"category":null,"text":"INT Legs","seen":"2026-07-10T03:44:16.830Z","lastSeen":"2026-07-10T03:44:16.830Z","count":1},{"server":"PvE","player":"Faithwarden","plus":[],"stats":[],"category":"necklace","text":"chada for whatever reason it wont let me /tell you id like to buy the wisdom necklace please","seen":"2026-07-10T03:48:41.886Z","lastSeen":"2026-07-10T03:48:41.886Z","count":1},{"server":"PvP","player":"Norkog","plus":[],"stats":[],"category":"jewelery","text":"bst waist shoulder jewelery","seen":"2026-07-10T03:55:17.455Z","lastSeen":"2026-07-10T04:15:04.095Z","count":10},{"server":"PvP","player":"Nolletta","plus":[],"stats":["int","cha"],"category":"gear","text":"W/TB Int/Cha Gear Chest, Shoulder, Back, Feet PST stats/price","seen":"2026-07-10T03:57:28.716Z","lastSeen":"2026-07-10T04:04:04.102Z","count":3},{"server":"PvP","player":"Vicks","plus":[4],"stats":["str","sta","agi","dex","int","wis","cha"],"category":"necklace","text":"+4 Enchants: Bracer 20g(INT/STA/WIS/STR), Necklace 7(CHA/INT/WIS), Cloak 7g(AGI/8 CR/CR/MR/PR), Gloves 6g (AGI/DEX/8 CR/ER)","seen":"2026-07-10T04:21:44.454Z","lastSeen":"2026-07-10T04:21:44.454Z","count":1},{"server":"PvE","player":"Elcid","plus":[],"stats":["str","cha"],"category":null,"text":"Greater enchant: cha face and str belt","seen":"2026-07-10T04:21:44.454Z","lastSeen":"2026-07-10T04:23:57.158Z","count":2},{"server":"PvP","player":"Sheilaa","plus":[],"stats":[],"category":"gear","text":"BST gear","seen":"2026-07-10T04:28:22.928Z","lastSeen":"2026-07-10T04:34:59.410Z","count":4},{"server":"PvE","player":"Beldin","plus":[4,8],"stats":["int","cha"],"category":null,"text":"+4 int (head, bracers x2) or +8MR (shoulders, belt, legs, cloak) +4 Cha (mask)","seen":"2026-07-10T04:28:22.928Z","lastSeen":"2026-07-10T04:32:47.260Z","count":3},{"server":"PvP","player":"Vicks","plus":[],"stats":[],"category":"ring","text":"Magebloom/Shadeshroom/Whispering Sage/Ironroot/Nomads Grace/Carrion Beetle Eyes/Phantom Residue/Magic Frond/Clouded Crystallized Magic","seen":"2026-07-10T04:59:17.078Z","lastSeen":"2026-07-10T07:00:35.086Z","count":22},{"server":"PvP","player":"Golem","plus":[],"stats":[],"category":"shield","text":"high end plate chest, legs, helm and shield","seen":"2026-07-10T04:59:17.078Z","lastSeen":"2026-07-10T05:14:45.010Z","count":13},{"server":"PvE","player":"Enchantresse","plus":[5],"stats":["int","cha"],"category":"ring","text":"+5 int/cha rings+necklace","seen":"2026-07-10T05:19:08.502Z","lastSeen":"2026-07-10T05:30:08.030Z","count":3},{"server":"PvE","player":"Dyscordia","plus":[4],"stats":["cha"],"category":"jewelry","text":"+4 cha enchants for jewelry - pst","seen":"2026-07-10T05:19:08.502Z","lastSeen":"2026-07-10T05:25:44.807Z","count":4},{"server":"PvP","player":"Vicks","plus":[],"stats":[],"category":"ring","text":"Magebloom/Shadeshroom/ Whispering Sage/Ironroot/Nomads Grace/Carrion Beetle Eyes/Phantom Residue/Magic Frond/Clouded Crystallized Magic","seen":"2026-07-10T05:21:20.822Z","lastSeen":"2026-07-10T06:31:43.761Z","count":4},{"server":"PvE","player":"Kosmopolitan","plus":[4],"stats":["cha"],"category":null,"text":"+4 CHA enchants.. face and x","seen":"2026-07-10T05:21:20.822Z","lastSeen":"2026-07-10T05:25:44.807Z","count":3},{"server":"PvE","player":"Boomtheeraser","plus":[4],"stats":["int"],"category":null,"text":"+4 int enchant for bracer","seen":"2026-07-10T05:25:44.807Z","lastSeen":"2026-07-10T05:27:56.358Z","count":2},{"server":"PvE","player":"Aequitasium","plus":[],"stats":[],"category":"jewelry","text":"inlaid ruby copper jewelry. pst","seen":"2026-07-10T05:27:56.358Z","lastSeen":"2026-07-10T05:27:56.358Z","count":1},{"server":"PvE","player":"Elwinn","plus":[],"stats":[],"category":"ring","text":"Jam, can you bring dru items with you next time?","seen":"2026-07-10T05:36:43.040Z","lastSeen":"2026-07-10T05:38:55.558Z","count":2},{"server":"PvP","player":"Vicks","plus":[],"stats":[],"category":"ring","text":"Magebloom/Shadeshroom/Whispering Sage/Ironroot/Nomads Grace/Carrion Beetle Eyes/Phantom Residue/ Magic Frond/Clouded Crystallized Magic","seen":"2026-07-10T06:05:16.054Z","lastSeen":"2026-07-10T06:33:57.198Z","count":3},{"server":"PvE","player":"Shanksalot","plus":[],"stats":["str","dex"],"category":"ring","text":"str/dex rings pst","seen":"2026-07-10T06:16:14.304Z","lastSeen":"2026-07-10T06:33:57.198Z","count":5},{"server":"PvE","player":"Foepnaas","plus":[],"stats":["str","agi"],"category":"necklace","text":"STR AGI necklace","seen":"2026-07-10T06:22:51.497Z","lastSeen":"2026-07-10T06:25:04.415Z","count":2},{"server":"PvP","player":"Mafzil","plus":[4],"stats":["cha"],"category":"ring","text":"+4 cha enchant to earing","seen":"2026-07-10T06:25:04.415Z","lastSeen":"2026-07-10T06:42:48.870Z","count":9},{"server":"PvP","player":"Vicks","plus":[],"stats":[],"category":"ring","text":"Magebloom/Shadeshroom/ Whispering Sage/Ironroot/Nomads Grace/Carrion Beetle Eyes/Phantom Residue/ Magic Frond/Clouded Crystallized Magic","seen":"2026-07-10T06:27:16.926Z","lastSeen":"2026-07-10T06:27:16.926Z","count":1},{"server":"PvP","player":"Idylll","plus":[],"stats":[],"category":"jewelery","text":"7/7 Jewelery Set paying 35g","seen":"2026-07-10T08:02:07.452Z","lastSeen":"2026-07-10T08:19:37.086Z","count":9},{"server":"PvP","player":"Blvck","plus":[],"stats":[],"category":"gear","text":"tanky fighter gear, or strong 2h pst","seen":"2026-07-10T08:08:40.807Z","lastSeen":"2026-07-10T10:07:10.807Z","count":59},{"server":"PvP","player":"Ebola","plus":[],"stats":["str","dex"],"category":"jewelry","text":"str/dex jewelry","seen":"2026-07-10T08:17:25.718Z","lastSeen":"2026-07-10T08:28:22.742Z","count":6},{"server":"PvE","player":"Glorfindel","plus":[],"stats":[],"category":"gear","text":"looking for bst gear","seen":"2026-07-10T08:21:48.814Z","lastSeen":"2026-07-10T08:24:00.016Z","count":2},{"server":"PvE","player":"Glorftindel","plus":[],"stats":[],"category":"gear","text":"looking for bst gear","seen":"2026-07-10T08:26:11.542Z","lastSeen":"2026-07-10T08:28:22.742Z","count":2},{"server":"PvP","player":"Esoderic","plus":[],"stats":["str"],"category":null,"text":"str enchants","seen":"2026-07-10T09:16:34.294Z","lastSeen":"2026-07-10T09:47:23.158Z","count":15},{"server":"PvP","player":"Evildragon","plus":[2],"stats":[],"category":"ring","text":"making bronze (+2/+2) earrings 10s each ... send a /tell with what stats you seek","seen":"2026-07-10T09:23:10.502Z","lastSeen":"2026-07-10T10:26:55.598Z","count":51},{"server":"PvE","player":"Dyscordia","plus":[4],"stats":["cha"],"category":"ring","text":"+4 cha enchants for ears and rings - pst","seen":"2026-07-10T09:25:22.606Z","lastSeen":"2026-07-10T10:00:33.846Z","count":7},{"server":"PvE","player":"Glorfindel","plus":[],"stats":[],"category":"gear","text":"bst gear","seen":"2026-07-10T09:25:22.606Z","lastSeen":"2026-07-10T09:29:46.430Z","count":3},{"server":"PvE","player":"Engins","plus":[],"stats":[],"category":"ring","text":"|Inlaid Peridot Bronze Ring] 20s","seen":"2026-07-10T09:27:34.807Z","lastSeen":"2026-07-10T09:27:34.807Z","count":1},{"server":"PvP","player":"Evildragon","plus":[2],"stats":[],"category":"ring","text":"last call ... making bronze (+2/+2) earrings 10s each ... send a /tell with what stats you seek","seen":"2026-07-10T09:49:35.318Z","lastSeen":"2026-07-10T10:44:29.809Z","count":26},{"server":"PvP","player":"Evildragon","plus":[2],"stats":[],"category":"ring","text":"making bronze (+2/+2) earrings 1Us each ... send a /tell with what stats you seek","seen":"2026-07-10T09:51:46.291Z","lastSeen":"2026-07-10T10:04:58.198Z","count":7},{"server":"PvE","player":"Dyscordia","plus":[4],"stats":["cha"],"category":"ring","text":"TB +4 cha enchants for ears and rings - pst","seen":"2026-07-10T09:56:09.262Z","lastSeen":"2026-07-10T10:02:46.158Z","count":2},{"server":"PvE","player":"Glorfindel","plus":[],"stats":[],"category":"gear","text":"bst gear leather strength","seen":"2026-07-10T10:53:14.902Z","lastSeen":"2026-07-10T10:57:37.046Z","count":3},{"server":"PvE","player":"Glorfindel","plus":[],"stats":[],"category":"gear","text":"beastmaster gear","seen":"2026-07-10T10:55:25.534Z","lastSeen":"2026-07-10T11:04:11.809Z","count":5},{"server":"PvE","player":"Glorfindel","plus":[],"stats":["str"],"category":"armor","text":"leather str armor","seen":"2026-07-10T11:10:48.454Z","lastSeen":"2026-07-10T11:13:00.528Z","count":2},{"server":"PvP","player":"Atadru","plus":[],"stats":[],"category":"gear","text":"low level bard gear PST item/price","seen":"2026-07-10T11:17:24.809Z","lastSeen":"2026-07-10T11:52:40.406Z","count":12},{"server":"PvE","player":"Stakilm","plus":[],"stats":["int"],"category":null,"text":"INT wrists & mask","seen":"2026-07-10T11:17:24.809Z","lastSeen":"2026-07-10T11:19:36.886Z","count":2},{"server":"PvE","player":"Trevas","plus":[],"stats":["int"],"category":null,"text":"INT BELT, LEGS, GLOVES FOR ELE","seen":"2026-07-10T11:17:24.809Z","lastSeen":"2026-07-10T11:21:48.630Z","count":3},{"server":"PvE","player":"Trevas","plus":[],"stats":["int"],"category":"gear","text":"INT gear for ele belt, legs, gloves","seen":"2026-07-10T11:26:13.372Z","lastSeen":"2026-07-10T11:26:13.372Z","count":1},{"server":"PvE","player":"Stakilm","plus":[],"stats":["int"],"category":null,"text":"Int Mask & wrists~~Ele","seen":"2026-07-10T11:26:13.372Z","lastSeen":"2026-07-10T11:30:37.809Z","count":3},{"server":"PvP","player":"Sinmage","plus":[],"stats":[],"category":"gear","text":"t1 gear to D/E","seen":"2026-07-10T11:30:37.809Z","lastSeen":"2026-07-10T11:52:40.406Z","count":11},{"server":"PvE","player":"Trevas","plus":[],"stats":["int"],"category":"gear","text":"INT gear for ele belt, wrist, glove","seen":"2026-07-10T11:32:50.740Z","lastSeen":"2026-07-10T11:32:50.740Z","count":1}],"stats":{}}